[{"regs_in": {"ax": 28658, "bx": 51469, "cx": 55139, "dx": 7344, "si": 24076, "di": 42579, "bp": 49279, "sp": 65518}, "segs": {"ds": 8192, "es": 8704, "fs": 9216, "gs": 9728, "ss": 36864}, "mem_in": [[158487, 134]], "regs_out": {"eax": 28658, "ebx": 51469, "ecx": 55139, "edx": 7344, "esi": 24076, "edi": 42579, "ebp": 49279}, "mem_writes": [[655340, 242], [655341, 111], [655338, 0], [655339, 32]], "flags": {"cf": false, "pf": true, "af": false, "zf": true, "sf": false, "of": false}}, {"regs_in": {"ax": 16008, "bx": 12355, "cx": 27659, "dx": 21303, "si": 46065, "di": 19964, "bp": 59194, "sp": 65518}, "segs": {"ds": 8192, "es": 8704, "fs": 9216, "gs": 9728, "ss": 36864}, "mem_in": [[158487, 28]], "regs_out": {"eax": 16008, "ebx": 12355, "ecx": 27659, "edx": 21303, "esi": 46065, "edi": 19964, "ebp": 59194}, "mem_writes": [[655340, 136], [655341, 62], [655338, 0], [655339, 32]], "flags": {"cf": false, "pf": true, "af": false, "zf": true, "sf": false, "of": false}}, {"regs_in": {"ax": 61437, "bx": 22953, "cx": 23649, "dx": 22229, "si": 57281, "di": 17514, "bp": 10874, "sp": 65518}, "segs": {"ds": 8192, "es": 8704, "fs": 9216, "gs": 9728, "ss": 36864}, "mem_in": [[158487, 96]], "regs_out": {"eax": 61437, "ebx": 22953, "ecx": 23649, "edx": 22229, "esi": 57281, "edi": 17514, "ebp": 10874}, "mem_writes": [[655340, 253], [655341, 239], [655338, 0], [655339, 32]], "flags": {"cf": false, "pf": true, "af": false, "zf": true, "sf": false, "of": false}}, {"regs_in": {"ax": 11994, "bx": 28396, "cx": 45173, "dx": 64547, "si": 13580, "di": 21687, "bp": 19817, "sp": 65518}, "segs": {"ds": 8192, "es": 8704, "fs": 9216, "gs": 9728, "ss": 36864}, "mem_in": [[158487, 86]], "regs_out": {"eax": 11994, "ebx": 28396, "ecx": 45173, "edx": 64547, "esi": 13580, "edi": 21687, "ebp": 19817}, "mem_writes": [[655340, 218], [655341, 46], [655338, 0], [655339, 32]], "flags": {"cf": false, "pf": true, "af": false, "zf": true, "sf": false, "of": false}}, {"regs_in": {"ax": 23363, "bx": 55197, "cx": 45209, "dx": 55269, "si": 24400, "di": 29605, "bp": 34023, "sp": 65518}, "segs": {"ds": 8192, "es": 8704, "fs": 9216, "gs": 9728, "ss": 36864}, "mem_in": [[158487, 38]], "regs_out": {"eax": 23363, "ebx": 55197, "ecx": 45209, "edx": 55269, "esi": 24400, "edi": 29605, "ebp": 34023}, "mem_writes": [[655340, 67], [655341, 91], [655338, 0], [655339, 32]], "flags": {"cf": false, "pf": true, "af": false, "zf": true, "sf": false, "of": false}}, {"regs_in": {"ax": 62717, "bx": 27908, "cx": 27011, "dx": 64146, "si": 22484, "di": 42561, "bp": 979, "sp": 65518}, "segs": {"ds": 8192, "es": 8704, "fs": 9216, "gs": 9728, "ss": 36864}, "mem_in": [[158487, 240]], "regs_out": {"eax": 62717, "ebx": 27908, "ecx": 27011, "edx": 64146, "esi": 22484, "edi": 42561, "ebp": 979}, "mem_writes": [[655340, 253], [655341, 244], [655338, 0], [655339, 32]], "flags": {"cf": false, "pf": true, "af": false, "zf": true, "sf": false, "of": false}}, {"regs_in": {"ax": 29727, "bx": 41428, "cx": 22886, "dx": 52069, "si": 9331, "di": 60619, "bp": 48642, "sp": 65518}, "segs": {"ds": 8192, "es": 8704, "fs": 9216, "gs": 9728, "ss": 36864}, "mem_in": [[158487, 21]], "regs_out": {"eax": 29727, "ebx": 41428, "ecx": 22886, "edx": 52069, "esi": 9331, "edi": 60619, "ebp": 48642}, "mem_writes": [[655340, 31], [655341, 116], [655338, 0], [655339, 32]], "flags": {"cf": false, "pf": false, "af": false, "zf": false, "sf": false, "of": false}}, {"regs_in": {"ax": 7809, "bx": 34575, "cx": 34884, "dx": 47563, "si": 17515, "di": 600, "bp": 13727, "sp": 65518}, "segs": {"ds": 8192, "es": 8704, "fs": 9216, "gs": 9728, "ss": 36864}, "mem_in": [[158487, 72]], "regs_out": {"eax": 7809, "ebx": 34575, "ecx": 34884, "edx": 47563, "esi": 17515, "edi": 600, "ebp": 13727}, "mem_writes": [[655340, 129], [655341, 30], [655338, 0], [655339, 32]], "flags": {"cf": false, "pf": true, "af": false, "zf": true, "sf": false, "of": false}}, {"regs_in": {"ax": 30843, "bx": 13139, "cx": 58405, "dx": 2356, "si": 54707, "di": 28651, "bp": 22907, "sp": 65518}, "segs": {"ds": 8192, "es": 8704, "fs": 9216, "gs": 9728, "ss": 36864}, "mem_in": [[158487, 239]], "regs_out": {"eax": 30843, "ebx": 13139, "ecx": 58405, "edx": 2356, "esi": 54707, "edi": 28651, "ebp": 22907}, "mem_writes": [[655340, 123], [655341, 120], [655338, 0], [655339, 32]], "flags": {"cf": false, "pf": false, "af": false, "zf": false, "sf": false, "of": false}}, {"regs_in": {"ax": 13923, "bx": 63841, "cx": 41849, "dx": 13783, "si": 5692, "di": 26083, "bp": 28616, "sp": 65518}, "segs": {"ds": 8192, "es": 8704, "fs": 9216, "gs": 9728, "ss": 36864}, "mem_in": [[158487, 22]], "regs_out": {"eax": 13923, "ebx": 63841, "ecx": 41849, "edx": 13783, "esi": 5692, "edi": 26083, "ebp": 28616}, "mem_writes": [[655340, 99], [655341, 54], [655338, 0], [655339, 32]], "flags": {"cf": false, "pf": true, "af": false, "zf": true, "sf": false, "of": false}}, {"regs_in": {"ax": 27603, "bx": 53243, "cx": 12102, "dx": 41695, "si": 43001, "di": 7946, "bp": 4968, "sp": 65518}, "segs": {"ds": 8192, "es": 8704, "fs": 9216, "gs": 9728, "ss": 36864}, "mem_in": [[158487, 70]], "regs_out": {"eax": 27603, "ebx": 53243, "ecx": 12102, "edx": 41695, "esi": 43001, "edi": 7946, "ebp": 4968}, "mem_writes": [[655340, 211], [655341, 107], [655338, 0], [655339, 32]], "flags": {"cf": false, "pf": true, "af": false, "zf": true, "sf": false, "of": false}}, {"regs_in": {"ax": 957, "bx": 3475, "cx": 62080, "dx": 22688, "si": 4139, "di": 48945, "bp": 4141, "sp": 65518}, "segs": {"ds": 8192, "es": 8704, "fs": 9216, "gs": 9728, "ss": 36864}, "mem_in": [[158487, 70]], "regs_out": {"eax": 957, "ebx": 3475, "ecx": 62080, "edx": 22688, "esi": 4139, "edi": 48945, "ebp": 4141}, "mem_writes": [[655340, 189], [655341, 3], [655338, 0], [655339, 32]], "flags": {"cf": false, "pf": true, "af": false, "zf": true, "sf": false, "of": false}}, {"regs_in": {"ax": 14618, "bx": 38860, "cx": 28646, "dx": 30516, "si": 32786, "di": 28448, "bp": 15761, "sp": 65518}, "segs": {"ds": 8192, "es": 8704, "fs": 9216, "gs": 9728, "ss": 36864}, "mem_in": [[158487, 176]], "regs_out": {"eax": 14618, "ebx": 38860, "ecx": 28646, "edx": 30516, "esi": 32786, "edi": 28448, "ebp": 15761}, "mem_writes": [[655340, 26], [655341, 57], [655338, 0], [655339, 32]], "flags": {"cf": false, "pf": true, "af": false, "zf": true, "sf": false, "of": false}}, {"regs_in": {"ax": 52190, "bx": 38671, "cx": 37854, "dx": 13548, "si": 40223, "di": 43673, "bp": 13428, "sp": 65518}, "segs": {"ds": 8192, "es": 8704, "fs": 9216, "gs": 9728, "ss": 36864}, "mem_in": [[158487, 72]], "regs_out": {"eax": 52190, "ebx": 38671, "ecx": 37854, "edx": 13548, "esi": 40223, "edi": 43673, "ebp": 13428}, "mem_writes": [[655340, 222], [655341, 203], [655338, 0], [655339, 32]], "flags": {"cf": false, "pf": true, "af": false, "zf": true, "sf": false, "of": false}}, {"regs_in": {"ax": 46765, "bx": 12256, "cx": 23006, "dx": 50247, "si": 35907, "di": 16876, "bp": 54739, "sp": 65518}, "segs": {"ds": 8192, "es": 8704, "fs": 9216, "gs": 9728, "ss": 36864}, "mem_in": [[158487, 254]], "regs_out": {"eax": 46765, "ebx": 12256, "ecx": 23006, "edx": 50247, "esi": 35907, "edi": 16876, "ebp": 54739}, "mem_writes": [[655340, 173], [655341, 182], [655338, 0], [655339, 32]], "flags": {"cf": false, "pf": true, "af": false, "zf": true, "sf": false, "of": false}}, {"regs_in": {"ax": 31361, "bx": 47572, "cx": 6730, "dx": 558, "si": 35453, "di": 27962, "bp": 11667, "sp": 65518}, "segs": {"ds": 8192, "es": 8704, "fs": 9216, "gs": 9728, "ss": 36864}, "mem_in": [[158487, 51]], "regs_out": {"eax": 31361, "ebx": 47572, "ecx": 6730, "edx": 558, "esi": 35453, "edi": 27962, "ebp": 11667}, "mem_writes": [[655340, 129], [655341, 122], [655338, 0], [655339, 32]], "flags": {"cf": false, "pf": false, "af": false, "zf": false, "sf": false, "of": false}}, {"regs_in": {"ax": 27531, "bx": 42849, "cx": 55500, "dx": 45692, "si": 65158, "di": 5901, "bp": 40520, "sp": 65518}, "segs": {"ds": 8192, "es": 8704, "fs": 9216, "gs": 9728, "ss": 36864}, "mem_in": [[158487, 149]], "regs_out": {"eax": 27531, "ebx": 42849, "ecx": 55500, "edx": 45692, "esi": 65158, "edi": 5901, "ebp": 40520}, "mem_writes": [[655340, 139], [655341, 107], [655338, 0], [655339, 32]], "flags": {"cf": false, "pf": false, "af": false, "zf": false, "sf": false, "of": false}}, {"regs_in": {"ax": 13123, "bx": 36389, "cx": 3687, "dx": 42355, "si": 48716, "di": 28664, "bp": 36458, "sp": 65518}, "segs": {"ds": 8192, "es": 8704, "fs": 9216, "gs": 9728, "ss": 36864}, "mem_in": [[158487, 22]], "regs_out": {"eax": 13123, "ebx": 36389, "ecx": 3687, "edx": 42355, "esi": 48716, "edi": 28664, "ebp": 36458}, "mem_writes": [[655340, 67], [655341, 51], [655338, 0], [655339, 32]], "flags": {"cf": false, "pf": true, "af": false, "zf": true, "sf": false, "of": false}}, {"regs_in": {"ax": 61690, "bx": 1856, "cx": 53826, "dx": 18113, "si": 43491, "di": 30247, "bp": 50474, "sp": 65518}, "segs": {"ds": 8192, "es": 8704, "fs": 9216, "gs": 9728, "ss": 36864}, "mem_in": [[158487, 231]], "regs_out": {"eax": 61690, "ebx": 1856, "ecx": 53826, "edx": 18113, "esi": 43491, "edi": 30247, "ebp": 50474}, "mem_writes": [[655340, 250], [655341, 240], [655338, 0], [655339, 32]], "flags": {"cf": false, "pf": false, "af": false, "zf": false, "sf": false, "of": false}}, {"regs_in": {"ax": 11222, "bx": 1653, "cx": 36402, "dx": 39270, "si": 64782, "di": 43458, "bp": 59788, "sp": 65518}, "segs": {"ds": 8192, "es": 8704, "fs": 9216, "gs": 9728, "ss": 36864}, "mem_in": [[158487, 55]], "regs_out": {"eax": 11222, "ebx": 1653, "ecx": 36402, "edx": 39270, "esi": 64782, "edi": 43458, "ebp": 59788}, "mem_writes": [[655340, 214], [655341, 43], [655338, 0], [655339, 32]], "flags": {"cf": false, "pf": false, "af": false, "zf": false, "sf": false, "of": false}}, {"regs_in": {"ax": 17389, "bx": 52323, "cx": 35170, "dx": 40820, "si": 7296, "di": 2954, "bp": 45428, "sp": 65518}, "segs": {"ds": 8192, "es": 8704, "fs": 9216, "gs": 9728, "ss": 36864}, "mem_in": [[158487, 109]], "regs_out": {"eax": 17389, "ebx": 52323, "ecx": 35170, "edx": 40820, "esi": 7296, "edi": 2954, "ebp": 45428}, "mem_writes": [[655340, 237], [655341, 67], [655338, 0], [655339, 32]], "flags": {"cf": false, "pf": false, "af": false, "zf": false, "sf": false, "of": false}}, {"regs_in": {"ax": 27078, "bx": 44726, "cx": 61735, "dx": 17722, "si": 15187, "di": 63099, "bp": 34134, "sp": 65518}, "segs": {"ds": 8192, "es": 8704, "fs": 9216, "gs": 9728, "ss": 36864}, "mem_in": [[158487, 22]], "regs_out": {"eax": 27078, "ebx": 44726, "ecx": 61735, "edx": 17722, "esi": 15187, "edi": 63099, "ebp": 34134}, "mem_writes": [[655340, 198], [655341, 105], [655338, 0], [655339, 32]], "flags": {"cf": false, "pf": true, "af": false, "zf": true, "sf": false, "of": false}}, {"regs_in": {"ax": 58284, "bx": 31873, "cx": 43179, "dx": 27052, "si": 47068, "di": 36579, "bp": 15319, "sp": 65518}, "segs": {"ds": 8192, "es": 8704, "fs": 9216, "gs": 9728, "ss": 36864}, "mem_in": [[158487, 49]], "regs_out": {"eax": 58284, "ebx": 31873, "ecx": 43179, "edx": 27052, "esi": 47068, "edi": 36579, "ebp": 15319}, "mem_writes": [[655340, 172], [655341, 227], [655338, 0], [655339, 32]], "flags": {"cf": false, "pf": false, "af": false, "zf": false, "sf": false, "of": false}}, {"regs_in": {"ax": 52256, "bx": 55777, "cx": 52227, "dx": 17441, "si": 16212, "di": 19396, "bp": 46889, "sp": 65518}, "segs": {"ds": 8192, "es": 8704, "fs": 9216, "gs": 9728, "ss": 36864}, "mem_in": [[158487, 28]], "regs_out": {"eax": 52256, "ebx": 55777, "ecx": 52227, "edx": 17441, "esi": 16212, "edi": 19396, "ebp": 46889}, "mem_writes": [[655340, 32], [655341, 204], [655338, 0], [655339, 32]], "flags": {"cf": false, "pf": true, "af": false, "zf": true, "sf": false, "of": false}}, {"regs_in": {"ax": 2478, "bx": 53025, "cx": 60356, "dx": 21961, "si": 64289, "di": 65253, "bp": 950, "sp": 65518}, "segs": {"ds": 8192, "es": 8704, "fs": 9216, "gs": 9728, "ss": 36864}, "mem_in": [[158487, 253]], "regs_out": {"eax": 2478, "ebx": 53025, "ecx": 60356, "edx": 21961, "esi": 64289, "edi": 65253, "ebp": 950}, "mem_writes": [[655340, 174], [655341, 9], [655338, 0], [655339, 32]], "flags": {"cf": false, "pf": false, "af": false, "zf": false, "sf": false, "of": false}}, {"regs_in": {"ax": 52971, "bx": 49062, "cx": 51082, "dx": 55504, "si": 53213, "di": 2518, "bp": 45499, "sp": 65518}, "segs": {"ds": 8192, "es": 8704, "fs": 9216, "gs": 9728, "ss": 36864}, "mem_in": [[158487, 34]], "regs_out": {"eax": 52971, "ebx": 49062, "ecx": 51082, "edx": 55504, "esi": 53213, "edi": 2518, "ebp": 45499}, "mem_writes": [[655340, 235], [655341, 206], [655338, 0], [655339, 32]], "flags": {"cf": false, "pf": true, "af": false, "zf": true, "sf": false, "of": false}}, {"regs_in": {"ax": 33854, "bx": 59532, "cx": 46014, "dx": 18961, "si": 17499, "di": 11492, "bp": 26767, "sp": 65518}, "segs": {"ds": 8192, "es": 8704, "fs": 9216, "gs": 9728, "ss": 36864}, "mem_in": [[158487, 218]], "regs_out": {"eax": 33854, "ebx": 59532, "ecx": 46014, "edx": 18961, "esi": 17499, "edi": 11492, "ebp": 26767}, "mem_writes": [[655340, 62], [655341, 132], [655338, 0], [655339, 32]], "flags": {"cf": false, "pf": true, "af": false, "zf": true, "sf": false, "of": false}}, {"regs_in": {"ax": 39492, "bx": 53594, "cx": 3050, "dx": 33652, "si": 31649, "di": 28904, "bp": 14426, "sp": 65518}, "segs": {"ds": 8192, "es": 8704, "fs": 9216, "gs": 9728, "ss": 36864}, "mem_in": [[158487, 81]], "regs_out": {"eax": 39492, "ebx": 53594, "ecx": 3050, "edx": 33652, "esi": 31649, "edi": 28904, "ebp": 14426}, "mem_writes": [[655340, 68], [655341, 154], [655338, 0], [655339, 32]], "flags": {"cf": false, "pf": false, "af": false, "zf": false, "sf": false, "of": false}}, {"regs_in": {"ax": 63193, "bx": 55004, "cx": 10568, "dx": 14778, "si": 29985, "di": 41822, "bp": 60872, "sp": 65518}, "segs": {"ds": 8192, "es": 8704, "fs": 9216, "gs": 9728, "ss": 36864}, "mem_in": [[158487, 153]], "regs_out": {"eax": 63193, "ebx": 55004, "ecx": 10568, "edx": 14778, "esi": 29985, "edi": 41822, "ebp": 60872}, "mem_writes": [[655340, 217], [655341, 246], [655338, 0], [655339, 32]], "flags": {"cf": false, "pf": false, "af": false, "zf": false, "sf": false, "of": false}}, {"regs_in": {"ax": 30165, "bx": 56482, "cx": 21784, "dx": 40390, "si": 56360, "di": 24763, "bp": 27151, "sp": 65518}, "segs": {"ds": 8192, "es": 8704, "fs": 9216, "gs": 9728, "ss": 36864}, "mem_in": [[158487, 36]], "regs_out": {"eax": 30165, "ebx": 56482, "ecx": 21784, "edx": 40390, "esi": 56360, "edi": 24763, "ebp": 27151}, "mem_writes": [[655340, 213], [655341, 117], [655338, 0], [655339, 32]], "flags": {"cf": false, "pf": true, "af": false, "zf": true, "sf": false, "of": false}}, {"regs_in": {"ax": 32751, "bx": 923, "cx": 16367, "dx": 6383, "si": 20961, "di": 53540, "bp": 58676, "sp": 65518}, "segs": {"ds": 8192, "es": 8704, "fs": 9216, "gs": 9728, "ss": 36864}, "mem_in": [[158487, 240]], "regs_out": {"eax": 32751, "ebx": 923, "ecx": 16367, "edx": 6383, "esi": 20961, "edi": 53540, "ebp": 58676}, "mem_writes": [[655340, 239], [655341, 127], [655338, 0], [655339, 32]], "flags": {"cf": false, "pf": true, "af": false, "zf": true, "sf": false, "of": false}}, {"regs_in": {"ax": 30859, "bx": 26781, "cx": 57588, "dx": 27355, "si": 9292, "di": 61096, "bp": 38084, "sp": 65518}, "segs": {"ds": 8192, "es": 8704, "fs": 9216, "gs": 9728, "ss": 36864}, "mem_in": [[158487, 72]], "regs_out": {"eax": 30859, "ebx": 26781, "ecx": 57588, "edx": 27355, "esi": 9292, "edi": 61096, "ebp": 38084}, "mem_writes": [[655340, 139], [655341, 120], [655338, 0], [655339, 32]], "flags": {"cf": false, "pf": true, "af": false, "zf": true, "sf": false, "of": false}}, {"regs_in": {"ax": 6310, "bx": 50895, "cx": 34724, "dx": 56535, "si": 6419, "di": 35579, "bp": 63748, "sp": 65518}, "segs": {"ds": 8192, "es": 8704, "fs": 9216, "gs": 9728, "ss": 36864}, "mem_in": [[158487, 14]], "regs_out": {"eax": 6310, "ebx": 50895, "ecx": 34724, "edx": 56535, "esi": 6419, "edi": 35579, "ebp": 63748}, "mem_writes": [[655340, 166], [655341, 24], [655338, 0], [655339, 32]], "flags": {"cf": false, "pf": true, "af": false, "zf": true, "sf": false, "of": false}}, {"regs_in": {"ax": 43743, "bx": 148, "cx": 23852, "dx": 57941, "si": 12645, "di": 35047, "bp": 19058, "sp": 65518}, "segs": {"ds": 8192, "es": 8704, "fs": 9216, "gs": 9728, "ss": 36864}, "mem_in": [[158487, 56]], "regs_out": {"eax": 43743, "ebx": 148, "ecx": 23852, "edx": 57941, "esi": 12645, "edi": 35047, "ebp": 19058}, "mem_writes": [[655340, 223], [655341, 170], [655338, 0], [655339, 32]], "flags": {"cf": false, "pf": true, "af": false, "zf": true, "sf": false, "of": false}}, {"regs_in": {"ax": 2797, "bx": 58501, "cx": 19683, "dx": 15589, "si": 60065, "di": 37674, "bp": 20342, "sp": 65518}, "segs": {"ds": 8192, "es": 8704, "fs": 9216, "gs": 9728, "ss": 36864}, "mem_in": [[158487, 10]], "regs_out": {"eax": 2797, "ebx": 58501, "ecx": 19683, "edx": 15589, "esi": 60065, "edi": 37674, "ebp": 20342}, "mem_writes": [[655340, 237], [655341, 10], [655338, 0], [655339, 32]], "flags": {"cf": false, "pf": true, "af": false, "zf": true, "sf": false, "of": false}}, {"regs_in": {"ax": 12553, "bx": 24869, "cx": 42057, "dx": 14740, "si": 18352, "di": 17871, "bp": 42914, "sp": 65518}, "segs": {"ds": 8192, "es": 8704, "fs": 9216, "gs": 9728, "ss": 36864}, "mem_in": [[158487, 98]], "regs_out": {"eax": 12553, "ebx": 24869, "ecx": 42057, "edx": 14740, "esi": 18352, "edi": 17871, "ebp": 42914}, "mem_writes": [[655340, 9], [655341, 49], [655338, 0], [655339, 32]], "flags": {"cf": false, "pf": true, "af": false, "zf": true, "sf": false, "of": false}}, {"regs_in": {"ax": 37673, "bx": 59156, "cx": 24402, "dx": 47504, "si": 40944, "di": 47996, "bp": 18209, "sp": 65518}, "segs": {"ds": 8192, "es": 8704, "fs": 9216, "gs": 9728, "ss": 36864}, "mem_in": [[158487, 143]], "regs_out": {"eax": 37673, "ebx": 59156, "ecx": 24402, "edx": 47504, "esi": 40944, "edi": 47996, "ebp": 18209}, "mem_writes": [[655340, 41], [655341, 147], [655338, 0], [655339, 32]], "flags": {"cf": false, "pf": false, "af": false, "zf": false, "sf": false, "of": false}}, {"regs_in": {"ax": 21998, "bx": 2738, "cx": 29168, "dx": 37551, "si": 53255, "di": 29869, "bp": 9836, "sp": 65518}, "segs": {"ds": 8192, "es": 8704, "fs": 9216, "gs": 9728, "ss": 36864}, "mem_in": [[158487, 155]], "regs_out": {"eax": 21998, "ebx": 2738, "ecx": 29168, "edx": 37551, "esi": 53255, "edi": 29869, "ebp": 9836}, "mem_writes": [[655340, 238], [655341, 85], [655338, 0], [655339, 32]], "flags": {"cf": false, "pf": false, "af": false, "zf": false, "sf": false, "of": false}}, {"regs_in": {"ax": 42653, "bx": 54341, "cx": 9215, "dx": 56172, "si": 54439, "di": 54379, "bp": 10615, "sp": 65518}, "segs": {"ds": 8192, "es": 8704, "fs": 9216, "gs": 9728, "ss": 36864}, "mem_in": [[158487, 12]], "regs_out": {"eax": 42653, "ebx": 54341, "ecx": 9215, "edx": 56172, "esi": 54439, "edi": 54379, "ebp": 10615}, "mem_writes": [[655340, 157], [655341, 166], [655338, 0], [655339, 32]], "flags": {"cf": false, "pf": true, "af": false, "zf": true, "sf": false, "of": false}}, {"regs_in": {"ax": 21439, "bx": 47630, "cx": 29570, "dx": 39229, "si": 52000, "di": 49893, "bp": 22481, "sp": 65518}, "segs": {"ds": 8192, "es": 8704, "fs": 9216, "gs": 9728, "ss": 36864}, "mem_in": [[158487, 115]], "regs_out": {"eax": 21439, "ebx": 47630, "ecx": 29570, "edx": 39229, "esi": 52000, "edi": 49893, "ebp": 22481}, "mem_writes": [[655340, 191], [655341, 83], [655338, 0], [655339, 32]], "flags": {"cf": false, "pf": false, "af": false, "zf": false, "sf": false, "of": false}}, {"regs_in": {"ax": 32506, "bx": 10800, "cx": 6868, "dx": 60034, "si": 37014, "di": 14388, "bp": 53725, "sp": 65518}, "segs": {"ds": 8192, "es": 8704, "fs": 9216, "gs": 9728, "ss": 36864}, "mem_in": [[158487, 152]], "regs_out": {"eax": 32506, "ebx": 10800, "ecx": 6868, "edx": 60034, "esi": 37014, "edi": 14388, "ebp": 53725}, "mem_writes": [[655340, 250], [655341, 126], [655338, 0], [655339, 32]], "flags": {"cf": false, "pf": true, "af": false, "zf": true, "sf": false, "of": false}}, {"regs_in": {"ax": 34459, "bx": 8508, "cx": 45242, "dx": 41855, "si": 57595, "di": 15058, "bp": 61388, "sp": 65518}, "segs": {"ds": 8192, "es": 8704, "fs": 9216, "gs": 9728, "ss": 36864}, "mem_in": [], "regs_out": {"eax": 34459, "ebx": 8508, "ecx": 45242, "edx": 41855, "esi": 57595, "edi": 15058, "ebp": 61388}, "mem_writes": [[655340, 155], [655341, 134], [655338, 0], [655339, 32]], "flags": {"cf": false, "pf": true, "af": false, "zf": true, "sf": false, "of": false}}, {"regs_in": {"ax": 41908, "bx": 29876, "cx": 63761, "dx": 34169, "si": 43595, "di": 32013, "bp": 40114, "sp": 65518}, "segs": {"ds": 8192, "es": 8704, "fs": 9216, "gs": 9728, "ss": 36864}, "mem_in": [[158487, 39]], "regs_out": {"eax": 41908, "ebx": 29876, "ecx": 63761, "edx": 34169, "esi": 43595, "edi": 32013, "ebp": 40114}, "mem_writes": [[655340, 180], [655341, 163], [655338, 0], [655339, 32]], "flags": {"cf": false, "pf": false, "af": false, "zf": false, "sf": false, "of": false}}, {"regs_in": {"ax": 4507, "bx": 26867, "cx": 47437, "dx": 32993, "si": 64055, "di": 18713, "bp": 13301, "sp": 65518}, "segs": {"ds": 8192, "es": 8704, "fs": 9216, "gs": 9728, "ss": 36864}, "mem_in": [[158487, 125]], "regs_out": {"eax": 4507, "ebx": 26867, "ecx": 47437, "edx": 32993, "esi": 64055, "edi": 18713, "ebp": 13301}, "mem_writes": [[655340, 155], [655341, 17], [655338, 0], [655339, 32]], "flags": {"cf": false, "pf": false, "af": false, "zf": false, "sf": false, "of": false}}, {"regs_in": {"ax": 43208, "bx": 2634, "cx": 28315, "dx": 8389, "si": 45503, "di": 22074, "bp": 24147, "sp": 65518}, "segs": {"ds": 8192, "es": 8704, "fs": 9216, "gs": 9728, "ss": 36864}, "mem_in": [[158487, 95]], "regs_out": {"eax": 43208, "ebx": 2634, "ecx": 28315, "edx": 8389, "esi": 45503, "edi": 22074, "ebp": 24147}, "mem_writes": [[655340, 200], [655341, 168], [655338, 0], [655339, 32]], "flags": {"cf": false, "pf": false, "af": false, "zf": false, "sf": false, "of": false}}, {"regs_in": {"ax": 64432, "bx": 26545, "cx": 57729, "dx": 7258, "si": 34733, "di": 46360, "bp": 55935, "sp": 65518}, "segs": {"ds": 8192, "es": 8704, "fs": 9216, "gs": 9728, "ss": 36864}, "mem_in": [[158487, 241]], "regs_out": {"eax": 64432, "ebx": 26545, "ecx": 57729, "edx": 7258, "esi": 34733, "edi": 46360, "ebp": 55935}, "mem_writes": [[655340, 176], [655341, 251], [655338, 0], [655339, 32]], "flags": {"cf": false, "pf": false, "af": false, "zf": false, "sf": false, "of": false}}, {"regs_in": {"ax": 64402, "bx": 6367, "cx": 56116, "dx": 44352, "si": 42954, "di": 24134, "bp": 55014, "sp": 65518}, "segs": {"ds": 8192, "es": 8704, "fs": 9216, "gs": 9728, "ss": 36864}, "mem_in": [[158487, 246]], "regs_out": {"eax": 64402, "ebx": 6367, "ecx": 56116, "edx": 44352, "esi": 42954, "edi": 24134, "ebp": 55014}, "mem_writes": [[655340, 146], [655341, 251], [655338, 0], [655339, 32]], "flags": {"cf": false, "pf": true, "af": false, "zf": true, "sf": false, "of": false}}, {"regs_in": {"ax": 3953, "bx": 50377, "cx": 32605, "dx": 2709, "si": 53740, "di": 51314, "bp": 42365, "sp": 65518}, "segs": {"ds": 8192, "es": 8704, "fs": 9216, "gs": 9728, "ss": 36864}, "mem_in": [[158487, 147]], "regs_out": {"eax": 3953, "ebx": 50377, "ecx": 32605, "edx": 2709, "esi": 53740, "edi": 51314, "ebp": 42365}, "mem_writes": [[655340, 113], [655341, 15], [655338, 0], [655339, 32]], "flags": {"cf": false, "pf": false, "af": false, "zf": false, "sf": false, "of": false}}, {"regs_in": {"ax": 44542, "bx": 3211, "cx": 38995, "dx": 34489, "si": 45767, "di": 52801, "bp": 25006, "sp": 65518}, "segs": {"ds": 8192, "es": 8704, "fs": 9216, "gs": 9728, "ss": 36864}, "mem_in": [[158487, 40]], "regs_out": {"eax": 44542, "ebx": 3211, "ecx": 38995, "edx": 34489, "esi": 45767, "edi": 52801, "ebp": 25006}, "mem_writes": [[655340, 254], [655341, 173], [655338, 0], [655339, 32]], "flags": {"cf": false, "pf": true, "af": false, "zf": true, "sf": false, "of": false}}, {"regs_in": {"ax": 11094, "bx": 34262, "cx": 18008, "dx": 31779, "si": 25341, "di": 26840, "bp": 40039, "sp": 65518}, "segs": {"ds": 8192, "es": 8704, "fs": 9216, "gs": 9728, "ss": 36864}, "mem_in": [[158487, 138]], "regs_out": {"eax": 11094, "ebx": 34262, "ecx": 18008, "edx": 31779, "esi": 25341, "edi": 26840, "ebp": 40039}, "mem_writes": [[655340, 86], [655341, 43], [655338, 0], [655339, 32]], "flags": {"cf": false, "pf": true, "af": false, "zf": true, "sf": false, "of": false}}, {"regs_in": {"ax": 46243, "bx": 17027, "cx": 43591, "dx": 32679, "si": 12554, "di": 42501, "bp": 53161, "sp": 65518}, "segs": {"ds": 8192, "es": 8704, "fs": 9216, "gs": 9728, "ss": 36864}, "mem_in": [[158487, 93]], "regs_out": {"eax": 46243, "ebx": 17027, "ecx": 43591, "edx": 32679, "esi": 12554, "edi": 42501, "ebp": 53161}, "mem_writes": [[655340, 163], [655341, 180], [655338, 0], [655339, 32]], "flags": {"cf": false, "pf": false, "af": false, "zf": false, "sf": false, "of": false}}, {"regs_in": {"ax": 43271, "bx": 58342, "cx": 63158, "dx": 23132, "si": 12092, "di": 25261, "bp": 13939, "sp": 65518}, "segs": {"ds": 8192, "es": 8704, "fs": 9216, "gs": 9728, "ss": 36864}, "mem_in": [[158487, 229]], "regs_out": {"eax": 43271, "ebx": 58342, "ecx": 63158, "edx": 23132, "esi": 12092, "edi": 25261, "ebp": 13939}, "mem_writes": [[655340, 7], [655341, 169], [655338, 0], [655339, 32]], "flags": {"cf": false, "pf": false, "af": false, "zf": false, "sf": false, "of": false}}, {"regs_in": {"ax": 473, "bx": 1360, "cx": 53776, "dx": 49172, "si": 5697, "di": 4565, "bp": 38062, "sp": 65518}, "segs": {"ds": 8192, "es": 8704, "fs": 9216, "gs": 9728, "ss": 36864}, "mem_in": [[158487, 125]], "regs_out": {"eax": 473, "ebx": 1360, "ecx": 53776, "edx": 49172, "esi": 5697, "edi": 4565, "ebp": 38062}, "mem_writes": [[655340, 217], [655341, 1], [655338, 0], [655339, 32]], "flags": {"cf": false, "pf": false, "af": false, "zf": false, "sf": false, "of": false}}, {"regs_in": {"ax": 14420, "bx": 17719, "cx": 48459, "dx": 5042, "si": 3797, "di": 5088, "bp": 51567, "sp": 65518}, "segs": {"ds": 8192, "es": 8704, "fs": 9216, "gs": 9728, "ss": 36864}, "mem_in": [[158487, 81]], "regs_out": {"eax": 14420, "ebx": 17719, "ecx": 48459, "edx": 5042, "esi": 3797, "edi": 5088, "ebp": 51567}, "mem_writes": [[655340, 84], [655341, 56], [655338, 0], [655339, 32]], "flags": {"cf": false, "pf": false, "af": false, "zf": false, "sf": false, "of": false}}, {"regs_in": {"ax": 61210, "bx": 29493, "cx": 38416, "dx": 44805, "si": 16875, "di": 25687, "bp": 6130, "sp": 65518}, "segs": {"ds": 8192, "es": 8704, "fs": 9216, "gs": 9728, "ss": 36864}, "mem_in": [[158487, 231]], "regs_out": {"eax": 61210, "ebx": 29493, "ecx": 38416, "edx": 44805, "esi": 16875, "edi": 25687, "ebp": 6130}, "mem_writes": [[655340, 26], [655341, 239], [655338, 0], [655339, 32]], "flags": {"cf": false, "pf": false, "af": false, "zf": false, "sf": false, "of": false}}, {"regs_in": {"ax": 45162, "bx": 4933, "cx": 58602, "dx": 41807, "si": 25825, "di": 6717, "bp": 7289, "sp": 65518}, "segs": {"ds": 8192, "es": 8704, "fs": 9216, "gs": 9728, "ss": 36864}, "mem_in": [[158487, 174]], "regs_out": {"eax": 45162, "ebx": 4933, "ecx": 58602, "edx": 41807, "esi": 25825, "edi": 6717, "ebp": 7289}, "mem_writes": [[655340, 106], [655341, 176], [655338, 0], [655339, 32]], "flags": {"cf": false, "pf": true, "af": false, "zf": true, "sf": false, "of": false}}, {"regs_in": {"ax": 22365, "bx": 45201, "cx": 12243, "dx": 19460, "si": 45603, "di": 7705, "bp": 4780, "sp": 65518}, "segs": {"ds": 8192, "es": 8704, "fs": 9216, "gs": 9728, "ss": 36864}, "mem_in": [[158487, 30]], "regs_out": {"eax": 22365, "ebx": 45201, "ecx": 12243, "edx": 19460, "esi": 45603, "edi": 7705, "ebp": 4780}, "mem_writes": [[655340, 93], [655341, 87], [655338, 0], [655339, 32]], "flags": {"cf": false, "pf": true, "af": false, "zf": true, "sf": false, "of": false}}, {"regs_in": {"ax": 23870, "bx": 45152, "cx": 24876, "dx": 1919, "si": 21299, "di": 33547, "bp": 38147, "sp": 65518}, "segs": {"ds": 8192, "es": 8704, "fs": 9216, "gs": 9728, "ss": 36864}, "mem_in": [[158487, 44]], "regs_out": {"eax": 23870, "ebx": 45152, "ecx": 24876, "edx": 1919, "esi": 21299, "edi": 33547, "ebp": 38147}, "mem_writes": [[655340, 62], [655341, 93], [655338, 0], [655339, 32]], "flags": {"cf": false, "pf": true, "af": false, "zf": true, "sf": false, "of": false}}, {"regs_in": {"ax": 47797, "bx": 25721, "cx": 12679, "dx": 5304, "si": 6230, "di": 10562, "bp": 3052, "sp": 65518}, "segs": {"ds": 8192, "es": 8704, "fs": 9216, "gs": 9728, "ss": 36864}, "mem_in": [[158487, 192]], "regs_out": {"eax": 47797, "ebx": 25721, "ecx": 12679, "edx": 5304, "esi": 6230, "edi": 10562, "ebp": 3052}, "mem_writes": [[655340, 181], [655341, 186], [655338, 0], [655339, 32]], "flags": {"cf": false, "pf": true, "af": false, "zf": true, "sf": false, "of": false}}, {"regs_in": {"ax": 20026, "bx": 7321, "cx": 26890, "dx": 55480, "si": 23946, "di": 40514, "bp": 56549, "sp": 65518}, "segs": {"ds": 8192, "es": 8704, "fs": 9216, "gs": 9728, "ss": 36864}, "mem_in": [[158487, 226]], "regs_out": {"eax": 20026, "ebx": 7321, "ecx": 26890, "edx": 55480, "esi": 23946, "edi": 40514, "ebp": 56549}, "mem_writes": [[655340, 58], [655341, 78], [655338, 0], [655339, 32]], "flags": {"cf": false, "pf": true, "af": false, "zf": true, "sf": false, "of": false}}, {"regs_in": {"ax": 2782, "bx": 23681, "cx": 60821, "dx": 64891, "si": 57453, "di": 1661, "bp": 36487, "sp": 65518}, "segs": {"ds": 8192, "es": 8704, "fs": 9216, "gs": 9728, "ss": 36864}, "mem_in": [[158487, 20]], "regs_out": {"eax": 2782, "ebx": 23681, "ecx": 60821, "edx": 64891, "esi": 57453, "edi": 1661, "ebp": 36487}, "mem_writes": [[655340, 222], [655341, 10], [655338, 0], [655339, 32]], "flags": {"cf": false, "pf": true, "af": false, "zf": true, "sf": false, "of": false}}, {"regs_in": {"ax": 40283, "bx": 18049, "cx": 7127, "dx": 28796, "si": 8277, "di": 1455, "bp": 27117, "sp": 65518}, "segs": {"ds": 8192, "es": 8704, "fs": 9216, "gs": 9728, "ss": 36864}, "mem_in": [[158487, 137]], "regs_out": {"eax": 40283, "ebx": 18049, "ecx": 7127, "edx": 28796, "esi": 8277, "edi": 1455, "ebp": 27117}, "mem_writes": [[655340, 91], [655341, 157], [655338, 0], [655339, 32]], "flags": {"cf": false, "pf": false, "af": false, "zf": false, "sf": false, "of": false}}, {"regs_in": {"ax": 63569, "bx": 14352, "cx": 55151, "dx": 34995, "si": 60553, "di": 9618, "bp": 1161, "sp": 65518}, "segs": {"ds": 8192, "es": 8704, "fs": 9216, "gs": 9728, "ss": 36864}, "mem_in": [[158487, 32]], "regs_out": {"eax": 63569, "ebx": 14352, "ecx": 55151, "edx": 34995, "esi": 60553, "edi": 9618, "ebp": 1161}, "mem_writes": [[655340, 81], [655341, 248], [655338, 0], [655339, 32]], "flags": {"cf": false, "pf": true, "af": false, "zf": true, "sf": false, "of": false}}, {"regs_in": {"ax": 40680, "bx": 29872, "cx": 3372, "dx": 6266, "si": 34783, "di": 28535, "bp": 17740, "sp": 65518}, "segs": {"ds": 8192, "es": 8704, "fs": 9216, "gs": 9728, "ss": 36864}, "mem_in": [[158487, 17]], "regs_out": {"eax": 40680, "ebx": 29872, "ecx": 3372, "edx": 6266, "esi": 34783, "edi": 28535, "ebp": 17740}, "mem_writes": [[655340, 232], [655341, 158], [655338, 0], [655339, 32]], "flags": {"cf": false, "pf": false, "af": false, "zf": false, "sf": false, "of": false}}, {"regs_in": {"ax": 24252, "bx": 20380, "cx": 57693, "dx": 6465, "si": 16228, "di": 39742, "bp": 32661, "sp": 65518}, "segs": {"ds": 8192, "es": 8704, "fs": 9216, "gs": 9728, "ss": 36864}, "mem_in": [[158487, 84]], "regs_out": {"eax": 24252, "ebx": 20380, "ecx": 57693, "edx": 6465, "esi": 16228, "edi": 39742, "ebp": 32661}, "mem_writes": [[655340, 188], [655341, 94], [655338, 0], [655339, 32]], "flags": {"cf": false, "pf": true, "af": false, "zf": true, "sf": false, "of": false}}, {"regs_in": {"ax": 41120, "bx": 5663, "cx": 38385, "dx": 21010, "si": 30087, "di": 5290, "bp": 48387, "sp": 65518}, "segs": {"ds": 8192, "es": 8704, "fs": 9216, "gs": 9728, "ss": 36864}, "mem_in": [[158487, 144]], "regs_out": {"eax": 41120, "ebx": 5663, "ecx": 38385, "edx": 21010, "esi": 30087, "edi": 5290, "ebp": 48387}, "mem_writes": [[655340, 160], [655341, 160], [655338, 0], [655339, 32]], "flags": {"cf": false, "pf": true, "af": false, "zf": true, "sf": false, "of": false}}, {"regs_in": {"ax": 50177, "bx": 36970, "cx": 8113, "dx": 40868, "si": 1604, "di": 35451, "bp": 53811, "sp": 65518}, "segs": {"ds": 8192, "es": 8704, "fs": 9216, "gs": 9728, "ss": 36864}, "mem_in": [[158487, 33]], "regs_out": {"eax": 50177, "ebx": 36970, "ecx": 8113, "edx": 40868, "esi": 1604, "edi": 35451, "ebp": 53811}, "mem_writes": [[655340, 1], [655341, 196], [655338, 0], [655339, 32]], "flags": {"cf": false, "pf": false, "af": false, "zf": false, "sf": false, "of": false}}, {"regs_in": {"ax": 30477, "bx": 35650, "cx": 36988, "dx": 22096, "si": 14499, "di": 5117, "bp": 11550, "sp": 65518}, "segs": {"ds": 8192, "es": 8704, "fs": 9216, "gs": 9728, "ss": 36864}, "mem_in": [[158487, 158]], "regs_out": {"eax": 30477, "ebx": 35650, "ecx": 36988, "edx": 22096, "esi": 14499, "edi": 5117, "ebp": 11550}, "mem_writes": [[655340, 13], [655341, 119], [655338, 0], [655339, 32]], "flags": {"cf": false, "pf": true, "af": false, "zf": true, "sf": false, "of": false}}, {"regs_in": {"ax": 57006, "bx": 51413, "cx": 62221, "dx": 43678, "si": 38269, "di": 46004, "bp": 2992, "sp": 65518}, "segs": {"ds": 8192, "es": 8704, "fs": 9216, "gs": 9728, "ss": 36864}, "mem_in": [[158487, 78]], "regs_out": {"eax": 57006, "ebx": 51413, "ecx": 62221, "edx": 43678, "esi": 38269, "edi": 46004, "ebp": 2992}, "mem_writes": [[655340, 174], [655341, 222], [655338, 0], [655339, 32]], "flags": {"cf": false, "pf": true, "af": false, "zf": true, "sf": false, "of": false}}, {"regs_in": {"ax": 50752, "bx": 61652, "cx": 52513, "dx": 53406, "si": 49089, "di": 37431, "bp": 62870, "sp": 65518}, "segs": {"ds": 8192, "es": 8704, "fs": 9216, "gs": 9728, "ss": 36864}, "mem_in": [[158487, 186]], "regs_out": {"eax": 50752, "ebx": 61652, "ecx": 52513, "edx": 53406, "esi": 49089, "edi": 37431, "ebp": 62870}, "mem_writes": [[655340, 64], [655341, 198], [655338, 0], [655339, 32]], "flags": {"cf": false, "pf": true, "af": false, "zf": true, "sf": false, "of": false}}, {"regs_in": {"ax": 9416, "bx": 47716, "cx": 876, "dx": 52940, "si": 25293, "di": 27916, "bp": 46553, "sp": 65518}, "segs": {"ds": 8192, "es": 8704, "fs": 9216, "gs": 9728, "ss": 36864}, "mem_in": [[158487, 150]], "regs_out": {"eax": 9416, "ebx": 47716, "ecx": 876, "edx": 52940, "esi": 25293, "edi": 27916, "ebp": 46553}, "mem_writes": [[655340, 200], [655341, 36], [655338, 0], [655339, 32]], "flags": {"cf": false, "pf": true, "af": false, "zf": true, "sf": false, "of": false}}, {"regs_in": {"ax": 46197, "bx": 27504, "cx": 4480, "dx": 47741, "si": 56600, "di": 11316, "bp": 62679, "sp": 65518}, "segs": {"ds": 8192, "es": 8704, "fs": 9216, "gs": 9728, "ss": 36864}, "mem_in": [[158487, 137]], "regs_out": {"eax": 46197, "ebx": 27504, "ecx": 4480, "edx": 47741, "esi": 56600, "edi": 11316, "ebp": 62679}, "mem_writes": [[655340, 117], [655341, 180], [655338, 0], [655339, 32]], "flags": {"cf": false, "pf": false, "af": false, "zf": false, "sf": false, "of": false}}, {"regs_in": {"ax": 229, "bx": 14577, "cx": 3979, "dx": 6971, "si": 65047, "di": 58042, "bp": 1554, "sp": 65518}, "segs": {"ds": 8192, "es": 8704, "fs": 9216, "gs": 9728, "ss": 36864}, "mem_in": [[158487, 216]], "regs_out": {"eax": 229, "ebx": 14577, "ecx": 3979, "edx": 6971, "esi": 65047, "edi": 58042, "ebp": 1554}, "mem_writes": [[655340, 229], [655341, 0], [655338, 0], [655339, 32]], "flags": {"cf": false, "pf": true, "af": false, "zf": true, "sf": false, "of": false}}, {"regs_in": {"ax": 19117, "bx": 6743, "cx": 27134, "dx": 56576, "si": 13488, "di": 55911, "bp": 20904, "sp": 65518}, "segs": {"ds": 8192, "es": 8704, "fs": 9216, "gs": 9728, "ss": 36864}, "mem_in": [[158487, 117]], "regs_out": {"eax": 19117, "ebx": 6743, "ecx": 27134, "edx": 56576, "esi": 13488, "edi": 55911, "ebp": 20904}, "mem_writes": [[655340, 173], [655341, 74], [655338, 0], [655339, 32]], "flags": {"cf": false, "pf": false, "af": false, "zf": false, "sf": false, "of": false}}, {"regs_in": {"ax": 61795, "bx": 47422, "cx": 36541, "dx": 18427, "si": 33214, "di": 10368, "bp": 31136, "sp": 65518}, "segs": {"ds": 8192, "es": 8704, "fs": 9216, "gs": 9728, "ss": 36864}, "mem_in": [[158487, 231]], "regs_out": {"eax": 61795, "ebx": 47422, "ecx": 36541, "edx": 18427, "esi": 33214, "edi": 10368, "ebp": 31136}, "mem_writes": [[655340, 99], [655341, 241], [655338, 0], [655339, 32]], "flags": {"cf": false, "pf": false, "af": false, "zf": false, "sf": false, "of": false}}, {"regs_in": {"ax": 8327, "bx": 28571, "cx": 58486, "dx": 14801, "si": 50520, "di": 60503, "bp": 55750, "sp": 65518}, "segs": {"ds": 8192, "es": 8704, "fs": 9216, "gs": 9728, "ss": 36864}, "mem_in": [[158487, 175]], "regs_out": {"eax": 8327, "ebx": 28571, "ecx": 58486, "edx": 14801, "esi": 50520, "edi": 60503, "ebp": 55750}, "mem_writes": [[655340, 135], [655341, 32], [655338, 0], [655339, 32]], "flags": {"cf": false, "pf": false, "af": false, "zf": false, "sf": false, "of": false}}, {"regs_in": {"ax": 11798, "bx": 19927, "cx": 8616, "dx": 41733, "si": 41845, "di": 62336, "bp": 12334, "sp": 65518}, "segs": {"ds": 8192, "es": 8704, "fs": 9216, "gs": 9728, "ss": 36864}, "mem_in": [[158487, 74]], "regs_out": {"eax": 11798, "ebx": 19927, "ecx": 8616, "edx": 41733, "esi": 41845, "edi": 62336, "ebp": 12334}, "mem_writes": [[655340, 22], [655341, 46], [655338, 0], [655339, 32]], "flags": {"cf": false, "pf": true, "af": false, "zf": true, "sf": false, "of": false}}, {"regs_in": {"ax": 50459, "bx": 41454, "cx": 822, "dx": 28806, "si": 53411, "di": 63627, "bp": 38467, "sp": 65518}, "segs": {"ds": 8192, "es": 8704, "fs": 9216, "gs": 9728, "ss": 36864}, "mem_in": [[158487, 12]], "regs_out": {"eax": 50459, "ebx": 41454, "ecx": 822, "edx": 28806, "esi": 53411, "edi": 63627, "ebp": 38467}, "mem_writes": [[655340, 27], [655341, 197], [655338, 0], [655339, 32]], "flags": {"cf": false, "pf": true, "af": false, "zf": true, "sf": false, "of": false}}, {"regs_in": {"ax": 28457, "bx": 16137, "cx": 30263, "dx": 10309, "si": 33521, "di": 28329, "bp": 52155, "sp": 65518}, "segs": {"ds": 8192, "es": 8704, "fs": 9216, "gs": 9728, "ss": 36864}, "mem_in": [[158487, 146]], "regs_out": {"eax": 28457, "ebx": 16137, "ecx": 30263, "edx": 10309, "esi": 33521, "edi": 28329, "ebp": 52155}, "mem_writes": [[655340, 41], [655341, 111], [655338, 0], [655339, 32]], "flags": {"cf": false, "pf": true, "af": false, "zf": true, "sf": false, "of": false}}, {"regs_in": {"ax": 3688, "bx": 166, "cx": 24217, "dx": 28904, "si": 14538, "di": 49270, "bp": 34348, "sp": 65518}, "segs": {"ds": 8192, "es": 8704, "fs": 9216, "gs": 9728, "ss": 36864}, "mem_in": [[158487, 17]], "regs_out": {"eax": 3688, "ebx": 166, "ecx": 24217, "edx": 28904, "esi": 14538, "edi": 49270, "ebp": 34348}, "mem_writes": [[655340, 104], [655341, 14], [655338, 0], [655339, 32]], "flags": {"cf": false, "pf": false, "af": false, "zf": false, "sf": false, "of": false}}, {"regs_in": {"ax": 60726, "bx": 26650, "cx": 61322, "dx": 27555, "si": 18340, "di": 55270, "bp": 62027, "sp": 65518}, "segs": {"ds": 8192, "es": 8704, "fs": 9216, "gs": 9728, "ss": 36864}, "mem_in": [[158487, 252]], "regs_out": {"eax": 60726, "ebx": 26650, "ecx": 61322, "edx": 27555, "esi": 18340, "edi": 55270, "ebp": 62027}, "mem_writes": [[655340, 54], [655341, 237], [655338, 0], [655339, 32]], "flags": {"cf": false, "pf": true, "af": false, "zf": true, "sf": false, "of": false}}, {"regs_in": {"ax": 48785, "bx": 49779, "cx": 28470, "dx": 26031, "si": 61072, "di": 59623, "bp": 40155, "sp": 65518}, "segs": {"ds": 8192, "es": 8704, "fs": 9216, "gs": 9728, "ss": 36864}, "mem_in": [[158487, 177]], "regs_out": {"eax": 48785, "ebx": 49779, "ecx": 28470, "edx": 26031, "esi": 61072, "edi": 59623, "ebp": 40155}, "mem_writes": [[655340, 145], [655341, 190], [655338, 0], [655339, 32]], "flags": {"cf": false, "pf": false, "af": false, "zf": false, "sf": false, "of": false}}, {"regs_in": {"ax": 34242, "bx": 41421, "cx": 18931, "dx": 57393, "si": 5677, "di": 60076, "bp": 4482, "sp": 65518}, "segs": {"ds": 8192, "es": 8704, "fs": 9216, "gs": 9728, "ss": 36864}, "mem_in": [[158487, 24]], "regs_out": {"eax": 34242, "ebx": 41421, "ecx": 18931, "edx": 57393, "esi": 5677, "edi": 60076, "ebp": 4482}, "mem_writes": [[655340, 194], [655341, 133], [655338, 0], [655339, 32]], "flags": {"cf": false, "pf": true, "af": false, "zf": true, "sf": false, "of": false}}, {"regs_in": {"ax": 5566, "bx": 62582, "cx": 6874, "dx": 23563, "si": 60883, "di": 7577, "bp": 55424, "sp": 65518}, "segs": {"ds": 8192, "es": 8704, "fs": 9216, "gs": 9728, "ss": 36864}, "mem_in": [[158487, 104]], "regs_out": {"eax": 5566, "ebx": 62582, "ecx": 6874, "edx": 23563, "esi": 60883, "edi": 7577, "ebp": 55424}, "mem_writes": [[655340, 190], [655341, 21], [655338, 0], [655339, 32]], "flags": {"cf": false, "pf": true, "af": false, "zf": true, "sf": false, "of": false}}, {"regs_in": {"ax": 56425, "bx": 62288, "cx": 39813, "dx": 23782, "si": 37573, "di": 64344, "bp": 46032, "sp": 65518}, "segs": {"ds": 8192, "es": 8704, "fs": 9216, "gs": 9728, "ss": 36864}, "mem_in": [[158487, 125]], "regs_out": {"eax": 56425, "ebx": 62288, "ecx": 39813, "edx": 23782, "esi": 37573, "edi": 64344, "ebp": 46032}, "mem_writes": [[655340, 105], [655341, 220], [655338, 0], [655339, 32]], "flags": {"cf": false, "pf": false, "af": false, "zf": false, "sf": false, "of": false}}, {"regs_in": {"ax": 61297, "bx": 37532, "cx": 21531, "dx": 51687, "si": 34616, "di": 42295, "bp": 49818, "sp": 65518}, "segs": {"ds": 8192, "es": 8704, "fs": 9216, "gs": 9728, "ss": 36864}, "mem_in": [[158487, 255]], "regs_out": {"eax": 61297, "ebx": 37532, "ecx": 21531, "edx": 51687, "esi": 34616, "edi": 42295, "ebp": 49818}, "mem_writes": [[655340, 113], [655341, 239], [655338, 0], [655339, 32]], "flags": {"cf": false, "pf": false, "af": false, "zf": false, "sf": false, "of": false}}, {"regs_in": {"ax": 50291, "bx": 14154, "cx": 41932, "dx": 37046, "si": 52498, "di": 55560, "bp": 49318, "sp": 65518}, "segs": {"ds": 8192, "es": 8704, "fs": 9216, "gs": 9728, "ss": 36864}, "mem_in": [[158487, 133]], "regs_out": {"eax": 50291, "ebx": 14154, "ecx": 41932, "edx": 37046, "esi": 52498, "edi": 55560, "ebp": 49318}, "mem_writes": [[655340, 115], [655341, 196], [655338, 0], [655339, 32]], "flags": {"cf": false, "pf": false, "af": false, "zf": false, "sf": false, "of": false}}, {"regs_in": {"ax": 4259, "bx": 20225, "cx": 7087, "dx": 5745, "si": 6351, "di": 25327, "bp": 24351, "sp": 65518}, "segs": {"ds": 8192, "es": 8704, "fs": 9216, "gs": 9728, "ss": 36864}, "mem_in": [[158487, 4]], "regs_out": {"eax": 4259, "ebx": 20225, "ecx": 7087, "edx": 5745, "esi": 6351, "edi": 25327, "ebp": 24351}, "mem_writes": [[655340, 163], [655341, 16], [655338, 0], [655339, 32]], "flags": {"cf": false, "pf": true, "af": false, "zf": true, "sf": false, "of": false}}, {"regs_in": {"ax": 6807, "bx": 21090, "cx": 57804, "dx": 60150, "si": 40430, "di": 32071, "bp": 25905, "sp": 65518}, "segs": {"ds": 8192, "es": 8704, "fs": 9216, "gs": 9728, "ss": 36864}, "mem_in": [[158487, 216]], "regs_out": {"eax": 6807, "ebx": 21090, "ecx": 57804, "edx": 60150, "esi": 40430, "edi": 32071, "ebp": 25905}, "mem_writes": [[655340, 151], [655341, 26], [655338, 0], [655339, 32]], "flags": {"cf": false, "pf": true, "af": false, "zf": true, "sf": false, "of": false}}, {"regs_in": {"ax": 44881, "bx": 55454, "cx": 54181, "dx": 6549, "si": 21919, "di": 40995, "bp": 63910, "sp": 65518}, "segs": {"ds": 8192, "es": 8704, "fs": 9216, "gs": 9728, "ss": 36864}, "mem_in": [[158487, 103]], "regs_out": {"eax": 44881, "ebx": 55454, "ecx": 54181, "edx": 6549, "esi": 21919, "edi": 40995, "ebp": 63910}, "mem_writes": [[655340, 81], [655341, 175], [655338, 0], [655339, 32]], "flags": {"cf": false, "pf": false, "af": false, "zf": false, "sf": false, "of": false}}, {"regs_in": {"ax": 56059, "bx": 13633, "cx": 59196, "dx": 21116, "si": 13317, "di": 24103, "bp": 29254, "sp": 65518}, "segs": {"ds": 8192, "es": 8704, "fs": 9216, "gs": 9728, "ss": 36864}, "mem_in": [[158487, 234]], "regs_out": {"eax": 56059, "ebx": 13633, "ecx": 59196, "edx": 21116, "esi": 13317, "edi": 24103, "ebp": 29254}, "mem_writes": [[655340, 251], [655341, 218], [655338, 0], [655339, 32]], "flags": {"cf": false, "pf": true, "af": false, "zf": true, "sf": false, "of": false}}, {"regs_in": {"ax": 37423, "bx": 63017, "cx": 60155, "dx": 10211, "si": 41181, "di": 57953, "bp": 7720, "sp": 65518}, "segs": {"ds": 8192, "es": 8704, "fs": 9216, "gs": 9728, "ss": 36864}, "mem_in": [[158487, 29]], "regs_out": {"eax": 37423, "ebx": 63017, "ecx": 60155, "edx": 10211, "esi": 41181, "edi": 57953, "ebp": 7720}, "mem_writes": [[655340, 47], [655341, 146], [655338, 0], [655339, 32]], "flags": {"cf": false, "pf": false, "af": false, "zf": false, "sf": false, "of": false}}, {"regs_in": {"ax": 36259, "bx": 17458, "cx": 19289, "dx": 23817, "si": 4893, "di": 59164, "bp": 52591, "sp": 65518}, "segs": {"ds": 8192, "es": 8704, "fs": 9216, "gs": 9728, "ss": 36864}, "mem_in": [[158487, 161]], "regs_out": {"eax": 36259, "ebx": 17458, "ecx": 19289, "edx": 23817, "esi": 4893, "edi": 59164, "ebp": 52591}, "mem_writes": [[655340, 163], [655341, 141], [655338, 0], [655339, 32]], "flags": {"cf": false, "pf": false, "af": false, "zf": false, "sf": false, "of": false}}, {"regs_in": {"ax": 20029, "bx": 34590, "cx": 56462, "dx": 9111, "si": 31099, "di": 38567, "bp": 28565, "sp": 65518}, "segs": {"ds": 8192, "es": 8704, "fs": 9216, "gs": 9728, "ss": 36864}, "mem_in": [[158487, 98]], "regs_out": {"eax": 20029, "ebx": 34590, "ecx": 56462, "edx": 9111, "esi": 31099, "edi": 38567, "ebp": 28565}, "mem_writes": [[655340, 61], [655341, 78], [655338, 0], [655339, 32]], "flags": {"cf": false, "pf": true, "af": false, "zf": true, "sf": false, "of": false}}, {"regs_in": {"ax": 44065, "bx": 15237, "cx": 58275, "dx": 3319, "si": 425, "di": 16509, "bp": 1062, "sp": 65518}, "segs": {"ds": 8192, "es": 8704, "fs": 9216, "gs": 9728, "ss": 36864}, "mem_in": [[158487, 57]], "regs_out": {"eax": 44065, "ebx": 15237, "ecx": 58275, "edx": 3319, "esi": 425, "edi": 16509, "ebp": 1062}, "mem_writes": [[655340, 33], [655341, 172], [655338, 0], [655339, 32]], "flags": {"cf": false, "pf": false, "af": false, "zf": false, "sf": false, "of": false}}, {"regs_in": {"ax": 61785, "bx": 50515, "cx": 64277, "dx": 58859, "si": 39830, "di": 6323, "bp": 19026, "sp": 65518}, "segs": {"ds": 8192, "es": 8704, "fs": 9216, "gs": 9728, "ss": 36864}, "mem_in": [[158487, 134]], "regs_out": {"eax": 61785, "ebx": 50515, "ecx": 64277, "edx": 58859, "esi": 39830, "edi": 6323, "ebp": 19026}, "mem_writes": [[655340, 89], [655341, 241], [655338, 0], [655339, 32]], "flags": {"cf": false, "pf": true, "af": false, "zf": true, "sf": false, "of": false}}, {"regs_in": {"ax": 22004, "bx": 32159, "cx": 3193, "dx": 41963, "si": 41484, "di": 15654, "bp": 14035, "sp": 65518}, "segs": {"ds": 8192, "es": 8704, "fs": 9216, "gs": 9728, "ss": 36864}, "mem_in": [[158487, 185]], "regs_out": {"eax": 22004, "ebx": 32159, "ecx": 3193, "edx": 41963, "esi": 41484, "edi": 15654, "ebp": 14035}, "mem_writes": [[655340, 244], [655341, 85], [655338, 0], [655339, 32]], "flags": {"cf": false, "pf": false, "af": false, "zf": false, "sf": false, "of": false}}, {"regs_in": {"ax": 40415, "bx": 60090, "cx": 4610, "dx": 55115, "si": 14654, "di": 15348, "bp": 7528, "sp": 65518}, "segs": {"ds": 8192, "es": 8704, "fs": 9216, "gs": 9728, "ss": 36864}, "mem_in": [[158487, 116]], "regs_out": {"eax": 40415, "ebx": 60090, "ecx": 4610, "edx": 55115, "esi": 14654, "edi": 15348, "ebp": 7528}, "mem_writes": [[655340, 223], [655341, 157], [655338, 0], [655339, 32]], "flags": {"cf": false, "pf": true, "af": false, "zf": true, "sf": false, "of": false}}, {"regs_in": {"ax": 40486, "bx": 14811, "cx": 44911, "dx": 64810, "si": 44453, "di": 38276, "bp": 12408, "sp": 65518}, "segs": {"ds": 8192, "es": 8704, "fs": 9216, "gs": 9728, "ss": 36864}, "mem_in": [[158487, 66]], "regs_out": {"eax": 40486, "ebx": 14811, "ecx": 44911, "edx": 64810, "esi": 44453, "edi": 38276, "ebp": 12408}, "mem_writes": [[655340, 38], [655341, 158], [655338, 0], [655339, 32]], "flags": {"cf": false, "pf": true, "af": false, "zf": true, "sf": false, "of": false}}, {"regs_in": {"ax": 25388, "bx": 13074, "cx": 52593, "dx": 53981, "si": 46943, "di": 23497, "bp": 63305, "sp": 65518}, "segs": {"ds": 8192, "es": 8704, "fs": 9216, "gs": 9728, "ss": 36864}, "mem_in": [[158487, 132]], "regs_out": {"eax": 25388, "ebx": 13074, "ecx": 52593, "edx": 53981, "esi": 46943, "edi": 23497, "ebp": 63305}, "mem_writes": [[655340, 44], [655341, 99], [655338, 0], [655339, 32]], "flags": {"cf": false, "pf": true, "af": false, "zf": true, "sf": false, "of": false}}, {"regs_in": {"ax": 40424, "bx": 51678, "cx": 59074, "dx": 40038, "si": 58287, "di": 46905, "bp": 57585, "sp": 65518}, "segs": {"ds": 8192, "es": 8704, "fs": 9216, "gs": 9728, "ss": 36864}, "mem_in": [[158487, 5]], "regs_out": {"eax": 40424, "ebx": 51678, "ecx": 59074, "edx": 40038, "esi": 58287, "edi": 46905, "ebp": 57585}, "mem_writes": [[655340, 232], [655341, 157], [655338, 0], [655339, 32]], "flags": {"cf": false, "pf": false, "af": false, "zf": false, "sf": false, "of": false}}, {"regs_in": {"ax": 61305, "bx": 52848, "cx": 10430, "dx": 49298, "si": 45228, "di": 18400, "bp": 592, "sp": 65518}, "segs": {"ds": 8192, "es": 8704, "fs": 9216, "gs": 9728, "ss": 36864}, "mem_in": [[158487, 3]], "regs_out": {"eax": 61305, "ebx": 52848, "ecx": 10430, "edx": 49298, "esi": 45228, "edi": 18400, "ebp": 592}, "mem_writes": [[655340, 121], [655341, 239], [655338, 0], [655339, 32]], "flags": {"cf": false, "pf": false, "af": false, "zf": false, "sf": false, "of": false}}, {"regs_in": {"ax": 1340, "bx": 64031, "cx": 1407, "dx": 55791, "si": 46180, "di": 29098, "bp": 44306, "sp": 65518}, "segs": {"ds": 8192, "es": 8704, "fs": 9216, "gs": 9728, "ss": 36864}, "mem_in": [[158487, 228]], "regs_out": {"eax": 1340, "ebx": 64031, "ecx": 1407, "edx": 55791, "esi": 46180, "edi": 29098, "ebp": 44306}, "mem_writes": [[655340, 60], [655341, 5], [655338, 0], [655339, 32]], "flags": {"cf": false, "pf": true, "af": false, "zf": true, "sf": false, "of": false}}, {"regs_in": {"ax": 41144, "bx": 35523, "cx": 49703, "dx": 42166, "si": 3878, "di": 43147, "bp": 17950, "sp": 65518}, "segs": {"ds": 8192, "es": 8704, "fs": 9216, "gs": 9728, "ss": 36864}, "mem_in": [[158487, 254]], "regs_out": {"eax": 41144, "ebx": 35523, "ecx": 49703, "edx": 42166, "esi": 3878, "edi": 43147, "ebp": 17950}, "mem_writes": [[655340, 184], [655341, 160], [655338, 0], [655339, 32]], "flags": {"cf": false, "pf": true, "af": false, "zf": true, "sf": false, "of": false}}, {"regs_in": {"ax": 54723, "bx": 28787, "cx": 65280, "dx": 56705, "si": 47460, "di": 34879, "bp": 14452, "sp": 65518}, "segs": {"ds": 8192, "es": 8704, "fs": 9216, "gs": 9728, "ss": 36864}, "mem_in": [[158487, 108]], "regs_out": {"eax": 54723, "ebx": 28787, "ecx": 65280, "edx": 56705, "esi": 47460, "edi": 34879, "ebp": 14452}, "mem_writes": [[655340, 195], [655341, 213], [655338, 0], [655339, 32]], "flags": {"cf": false, "pf": true, "af": false, "zf": true, "sf": false, "of": false}}, {"regs_in": {"ax": 49017, "bx": 64125, "cx": 3141, "dx": 14571, "si": 42887, "di": 33626, "bp": 5812, "sp": 65518}, "segs": {"ds": 8192, "es": 8704, "fs": 9216, "gs": 9728, "ss": 36864}, "mem_in": [[158487, 193]], "regs_out": {"eax": 49017, "ebx": 64125, "ecx": 3141, "edx": 14571, "esi": 42887, "edi": 33626, "ebp": 5812}, "mem_writes": [[655340, 121], [655341, 191], [655338, 0], [655339, 32]], "flags": {"cf": false, "pf": false, "af": false, "zf": false, "sf": false, "of": false}}, {"regs_in": {"ax": 15497, "bx": 40893, "cx": 62284, "dx": 34027, "si": 282, "di": 45312, "bp": 62865, "sp": 65518}, "segs": {"ds": 8192, "es": 8704, "fs": 9216, "gs": 9728, "ss": 36864}, "mem_in": [[158487, 113]], "regs_out": {"eax": 15497, "ebx": 40893, "ecx": 62284, "edx": 34027, "esi": 282, "edi": 45312, "ebp": 62865}, "mem_writes": [[655340, 137], [655341, 60], [655338, 0], [655339, 32]], "flags": {"cf": false, "pf": false, "af": false, "zf": false, "sf": false, "of": false}}, {"regs_in": {"ax": 48979, "bx": 1388, "cx": 28740, "dx": 46729, "si": 59957, "di": 27189, "bp": 24747, "sp": 65518}, "segs": {"ds": 8192, "es": 8704, "fs": 9216, "gs": 9728, "ss": 36864}, "mem_in": [[158487, 196]], "regs_out": {"eax": 48979, "ebx": 1388, "ecx": 28740, "edx": 46729, "esi": 59957, "edi": 27189, "ebp": 24747}, "mem_writes": [[655340, 83], [655341, 191], [655338, 0], [655339, 32]], "flags": {"cf": false, "pf": true, "af": false, "zf": true, "sf": false, "of": false}}, {"regs_in": {"ax": 10429, "bx": 20866, "cx": 58172, "dx": 30612, "si": 10147, "di": 41804, "bp": 39952, "sp": 65518}, "segs": {"ds": 8192, "es": 8704, "fs": 9216, "gs": 9728, "ss": 36864}, "mem_in": [[158487, 46]], "regs_out": {"eax": 10429, "ebx": 20866, "ecx": 58172, "edx": 30612, "esi": 10147, "edi": 41804, "ebp": 39952}, "mem_writes": [[655340, 189], [655341, 40], [655338, 0], [655339, 32]], "flags": {"cf": false, "pf": true, "af": false, "zf": true, "sf": false, "of": false}}, {"regs_in": {"ax": 16248, "bx": 3168, "cx": 12939, "dx": 60890, "si": 49609, "di": 53869, "bp": 15954, "sp": 65518}, "segs": {"ds": 8192, "es": 8704, "fs": 9216, "gs": 9728, "ss": 36864}, "mem_in": [[158487, 220]], "regs_out": {"eax": 16248, "ebx": 3168, "ecx": 12939, "edx": 60890, "esi": 49609, "edi": 53869, "ebp": 15954}, "mem_writes": [[655340, 120], [655341, 63], [655338, 0], [655339, 32]], "flags": {"cf": false, "pf": true, "af": false, "zf": true, "sf": false, "of": false}}, {"regs_in": {"ax": 54844, "bx": 59066, "cx": 1812, "dx": 39869, "si": 4341, "di": 32826, "bp": 35237, "sp": 65518}, "segs": {"ds": 8192, "es": 8704, "fs": 9216, "gs": 9728, "ss": 36864}, "mem_in": [[158487, 169]], "regs_out": {"eax": 54844, "ebx": 59066, "ecx": 1812, "edx": 39869, "esi": 4341, "edi": 32826, "ebp": 35237}, "mem_writes": [[655340, 60], [655341, 214], [655338, 0], [655339, 32]], "flags": {"cf": false, "pf": false, "af": false, "zf": false, "sf": false, "of": false}}, {"regs_in": {"ax": 36616, "bx": 55713, "cx": 36219, "dx": 24234, "si": 51088, "di": 60370, "bp": 46497, "sp": 65518}, "segs": {"ds": 8192, "es": 8704, "fs": 9216, "gs": 9728, "ss": 36864}, "mem_in": [[158487, 198]], "regs_out": {"eax": 36616, "ebx": 55713, "ecx": 36219, "edx": 24234, "esi": 51088, "edi": 60370, "ebp": 46497}, "mem_writes": [[655340, 8], [655341, 143], [655338, 0], [655339, 32]], "flags": {"cf": false, "pf": true, "af": false, "zf": true, "sf": false, "of": false}}, {"regs_in": {"ax": 28424, "bx": 40207, "cx": 51146, "dx": 23448, "si": 57248, "di": 23913, "bp": 11632, "sp": 65518}, "segs": {"ds": 8192, "es": 8704, "fs": 9216, "gs": 9728, "ss": 36864}, "mem_in": [[158487, 237]], "regs_out": {"eax": 28424, "ebx": 40207, "ecx": 51146, "edx": 23448, "esi": 57248, "edi": 23913, "ebp": 11632}, "mem_writes": [[655340, 8], [655341, 111], [655338, 0], [655339, 32]], "flags": {"cf": false, "pf": false, "af": false, "zf": false, "sf": false, "of": false}}, {"regs_in": {"ax": 37302, "bx": 22776, "cx": 5798, "dx": 9212, "si": 20260, "di": 42263, "bp": 13144, "sp": 65518}, "segs": {"ds": 8192, "es": 8704, "fs": 9216, "gs": 9728, "ss": 36864}, "mem_in": [[158487, 88]], "regs_out": {"eax": 37302, "ebx": 22776, "ecx": 5798, "edx": 9212, "esi": 20260, "edi": 42263, "ebp": 13144}, "mem_writes": [[655340, 182], [655341, 145], [655338, 0], [655339, 32]], "flags": {"cf": false, "pf": true, "af": false, "zf": true, "sf": false, "of": false}}, {"regs_in": {"ax": 15093, "bx": 6830, "cx": 9261, "dx": 37090, "si": 9260, "di": 35595, "bp": 3827, "sp": 65518}, "segs": {"ds": 8192, "es": 8704, "fs": 9216, "gs": 9728, "ss": 36864}, "mem_in": [[158487, 35]], "regs_out": {"eax": 15093, "ebx": 6830, "ecx": 9261, "edx": 37090, "esi": 9260, "edi": 35595, "ebp": 3827}, "mem_writes": [[655340, 245], [655341, 58], [655338, 0], [655339, 32]], "flags": {"cf": false, "pf": false, "af": false, "zf": false, "sf": false, "of": false}}, {"regs_in": {"ax": 54587, "bx": 43452, "cx": 32815, "dx": 31418, "si": 15238, "di": 59402, "bp": 44919, "sp": 65518}, "segs": {"ds": 8192, "es": 8704, "fs": 9216, "gs": 9728, "ss": 36864}, "mem_in": [[158487, 221]], "regs_out": {"eax": 54587, "ebx": 43452, "ecx": 32815, "edx": 31418, "esi": 15238, "edi": 59402, "ebp": 44919}, "mem_writes": [[655340, 59], [655341, 213], [655338, 0], [655339, 32]], "flags": {"cf": false, "pf": false, "af": false, "zf": false, "sf": false, "of": false}}, {"regs_in": {"ax": 61620, "bx": 50256, "cx": 60477, "dx": 8245, "si": 54846, "di": 5212, "bp": 36196, "sp": 65518}, "segs": {"ds": 8192, "es": 8704, "fs": 9216, "gs": 9728, "ss": 36864}, "mem_in": [[158487, 137]], "regs_out": {"eax": 61620, "ebx": 50256, "ecx": 60477, "edx": 8245, "esi": 54846, "edi": 5212, "ebp": 36196}, "mem_writes": [[655340, 180], [655341, 240], [655338, 0], [655339, 32]], "flags": {"cf": false, "pf": false, "af": false, "zf": false, "sf": false, "of": false}}, {"regs_in": {"ax": 53132, "bx": 25309, "cx": 499, "dx": 24315, "si": 41121, "di": 28566, "bp": 1858, "sp": 65518}, "segs": {"ds": 8192, "es": 8704, "fs": 9216, "gs": 9728, "ss": 36864}, "mem_in": [[158487, 249]], "regs_out": {"eax": 53132, "ebx": 25309, "ecx": 499, "edx": 24315, "esi": 41121, "edi": 28566, "ebp": 1858}, "mem_writes": [[655340, 140], [655341, 207], [655338, 0], [655339, 32]], "flags": {"cf": false, "pf": false, "af": false, "zf": false, "sf": false, "of": false}}, {"regs_in": {"ax": 25925, "bx": 41972, "cx": 55170, "dx": 53834, "si": 27681, "di": 63046, "bp": 30067, "sp": 65518}, "segs": {"ds": 8192, "es": 8704, "fs": 9216, "gs": 9728, "ss": 36864}, "mem_in": [[158487, 57]], "regs_out": {"eax": 25925, "ebx": 41972, "ecx": 55170, "edx": 53834, "esi": 27681, "edi": 63046, "ebp": 30067}, "mem_writes": [[655340, 69], [655341, 101], [655338, 0], [655339, 32]], "flags": {"cf": false, "pf": false, "af": false, "zf": false, "sf": false, "of": false}}, {"regs_in": {"ax": 48167, "bx": 16849, "cx": 33430, "dx": 17743, "si": 58972, "di": 8156, "bp": 57781, "sp": 65518}, "segs": {"ds": 8192, "es": 8704, "fs": 9216, "gs": 9728, "ss": 36864}, "mem_in": [[158487, 132]], "regs_out": {"eax": 48167, "ebx": 16849, "ecx": 33430, "edx": 17743, "esi": 58972, "edi": 8156, "ebp": 57781}, "mem_writes": [[655340, 39], [655341, 188], [655338, 0], [655339, 32]], "flags": {"cf": false, "pf": true, "af": false, "zf": true, "sf": false, "of": false}}, {"regs_in": {"ax": 8480, "bx": 40668, "cx": 27461, "dx": 58309, "si": 46034, "di": 56057, "bp": 53037, "sp": 65518}, "segs": {"ds": 8192, "es": 8704, "fs": 9216, "gs": 9728, "ss": 36864}, "mem_in": [[158487, 1]], "regs_out": {"eax": 8480, "ebx": 40668, "ecx": 27461, "edx": 58309, "esi": 46034, "edi": 56057, "ebp": 53037}, "mem_writes": [[655340, 32], [655341, 33], [655338, 0], [655339, 32]], "flags": {"cf": false, "pf": false, "af": false, "zf": false, "sf": false, "of": false}}, {"regs_in": {"ax": 45579, "bx": 44431, "cx": 12999, "dx": 48354, "si": 17101, "di": 32709, "bp": 31382, "sp": 65518}, "segs": {"ds": 8192, "es": 8704, "fs": 9216, "gs": 9728, "ss": 36864}, "mem_in": [[158487, 210]], "regs_out": {"eax": 45579, "ebx": 44431, "ecx": 12999, "edx": 48354, "esi": 17101, "edi": 32709, "ebp": 31382}, "mem_writes": [[655340, 11], [655341, 178], [655338, 0], [655339, 32]], "flags": {"cf": false, "pf": true, "af": false, "zf": true, "sf": false, "of": false}}, {"regs_in": {"ax": 8418, "bx": 48445, "cx": 33622, "dx": 61285, "si": 22205, "di": 46, "bp": 43828, "sp": 65518}, "segs": {"ds": 8192, "es": 8704, "fs": 9216, "gs": 9728, "ss": 36864}, "mem_in": [[158487, 60]], "regs_out": {"eax": 8418, "ebx": 48445, "ecx": 33622, "edx": 61285, "esi": 22205, "edi": 46, "ebp": 43828}, "mem_writes": [[655340, 226], [655341, 32], [655338, 0], [655339, 32]], "flags": {"cf": false, "pf": true, "af": false, "zf": true, "sf": false, "of": false}}, {"regs_in": {"ax": 40171, "bx": 7307, "cx": 16338, "dx": 13789, "si": 53450, "di": 21994, "bp": 41307, "sp": 65518}, "segs": {"ds": 8192, "es": 8704, "fs": 9216, "gs": 9728, "ss": 36864}, "mem_in": [[158487, 26]], "regs_out": {"eax": 40171, "ebx": 7307, "ecx": 16338, "edx": 13789, "esi": 53450, "edi": 21994, "ebp": 41307}, "mem_writes": [[655340, 235], [655341, 156], [655338, 0], [655339, 32]], "flags": {"cf": false, "pf": true, "af": false, "zf": true, "sf": false, "of": false}}, {"regs_in": {"ax": 58184, "bx": 47795, "cx": 33543, "dx": 3183, "si": 30237, "di": 52605, "bp": 12055, "sp": 65518}, "segs": {"ds": 8192, "es": 8704, "fs": 9216, "gs": 9728, "ss": 36864}, "mem_in": [[158487, 60]], "regs_out": {"eax": 58184, "ebx": 47795, "ecx": 33543, "edx": 3183, "esi": 30237, "edi": 52605, "ebp": 12055}, "mem_writes": [[655340, 72], [655341, 227], [655338, 0], [655339, 32]], "flags": {"cf": false, "pf": true, "af": false, "zf": true, "sf": false, "of": false}}, {"regs_in": {"ax": 48701, "bx": 8534, "cx": 29225, "dx": 42768, "si": 2804, "di": 64259, "bp": 62082, "sp": 65518}, "segs": {"ds": 8192, "es": 8704, "fs": 9216, "gs": 9728, "ss": 36864}, "mem_in": [[158487, 88]], "regs_out": {"eax": 48701, "ebx": 8534, "ecx": 29225, "edx": 42768, "esi": 2804, "edi": 64259, "ebp": 62082}, "mem_writes": [[655340, 61], [655341, 190], [655338, 0], [655339, 32]], "flags": {"cf": false, "pf": true, "af": false, "zf": true, "sf": false, "of": false}}, {"regs_in": {"ax": 2218, "bx": 13454, "cx": 37533, "dx": 28031, "si": 40341, "di": 26452, "bp": 49478, "sp": 65518}, "segs": {"ds": 8192, "es": 8704, "fs": 9216, "gs": 9728, "ss": 36864}, "mem_in": [[158487, 146]], "regs_out": {"eax": 2218, "ebx": 13454, "ecx": 37533, "edx": 28031, "esi": 40341, "edi": 26452, "ebp": 49478}, "mem_writes": [[655340, 170], [655341, 8], [655338, 0], [655339, 32]], "flags": {"cf": false, "pf": true, "af": false, "zf": true, "sf": false, "of": false}}, {"regs_in": {"ax": 36509, "bx": 18524, "cx": 4788, "dx": 17676, "si": 39624, "di": 6222, "bp": 43563, "sp": 65518}, "segs": {"ds": 8192, "es": 8704, "fs": 9216, "gs": 9728, "ss": 36864}, "mem_in": [[158487, 54]], "regs_out": {"eax": 36509, "ebx": 18524, "ecx": 4788, "edx": 17676, "esi": 39624, "edi": 6222, "ebp": 43563}, "mem_writes": [[655340, 157], [655341, 142], [655338, 0], [655339, 32]], "flags": {"cf": false, "pf": true, "af": false, "zf": true, "sf": false, "of": false}}, {"regs_in": {"ax": 3643, "bx": 21259, "cx": 63893, "dx": 27761, "si": 59961, "di": 54138, "bp": 9983, "sp": 65518}, "segs": {"ds": 8192, "es": 8704, "fs": 9216, "gs": 9728, "ss": 36864}, "mem_in": [[158487, 10]], "regs_out": {"eax": 3643, "ebx": 21259, "ecx": 63893, "edx": 27761, "esi": 59961, "edi": 54138, "ebp": 9983}, "mem_writes": [[655340, 59], [655341, 14], [655338, 0], [655339, 32]], "flags": {"cf": false, "pf": true, "af": false, "zf": true, "sf": false, "of": false}}, {"regs_in": {"ax": 13784, "bx": 30979, "cx": 16119, "dx": 22912, "si": 19351, "di": 37960, "bp": 33099, "sp": 65518}, "segs": {"ds": 8192, "es": 8704, "fs": 9216, "gs": 9728, "ss": 36864}, "mem_in": [[158487, 32]], "regs_out": {"eax": 13784, "ebx": 30979, "ecx": 16119, "edx": 22912, "esi": 19351, "edi": 37960, "ebp": 33099}, "mem_writes": [[655340, 216], [655341, 53], [655338, 0], [655339, 32]], "flags": {"cf": false, "pf": true, "af": false, "zf": true, "sf": false, "of": false}}, {"regs_in": {"ax": 45719, "bx": 57225, "cx": 49987, "dx": 33565, "si": 55186, "di": 6875, "bp": 6762, "sp": 65518}, "segs": {"ds": 8192, "es": 8704, "fs": 9216, "gs": 9728, "ss": 36864}, "mem_in": [[158487, 237]], "regs_out": {"eax": 45719, "ebx": 57225, "ecx": 49987, "edx": 33565, "esi": 55186, "edi": 6875, "ebp": 6762}, "mem_writes": [[655340, 151], [655341, 178], [655338, 0], [655339, 32]], "flags": {"cf": false, "pf": false, "af": false, "zf": false, "sf": false, "of": false}}, {"regs_in": {"ax": 21588, "bx": 45176, "cx": 44131, "dx": 61875, "si": 10951, "di": 64145, "bp": 15495, "sp": 65518}, "segs": {"ds": 8192, "es": 8704, "fs": 9216, "gs": 9728, "ss": 36864}, "mem_in": [[158487, 81]], "regs_out": {"eax": 21588, "ebx": 45176, "ecx": 44131, "edx": 61875, "esi": 10951, "edi": 64145, "ebp": 15495}, "mem_writes": [[655340, 84], [655341, 84], [655338, 0], [655339, 32]], "flags": {"cf": false, "pf": false, "af": false, "zf": false, "sf": false, "of": false}}, {"regs_in": {"ax": 28662, "bx": 59465, "cx": 63468, "dx": 50570, "si": 64159, "di": 2923, "bp": 8963, "sp": 65518}, "segs": {"ds": 8192, "es": 8704, "fs": 9216, "gs": 9728, "ss": 36864}, "mem_in": [[158487, 97]], "regs_out": {"eax": 28662, "ebx": 59465, "ecx": 63468, "edx": 50570, "esi": 64159, "edi": 2923, "ebp": 8963}, "mem_writes": [[655340, 246], [655341, 111], [655338, 0], [655339, 32]], "flags": {"cf": false, "pf": false, "af": false, "zf": false, "sf": false, "of": false}}, {"regs_in": {"ax": 9607, "bx": 52891, "cx": 7353, "dx": 7406, "si": 28298, "di": 30578, "bp": 4694, "sp": 65518}, "segs": {"ds": 8192, "es": 8704, "fs": 9216, "gs": 9728, "ss": 36864}, "mem_in": [[158487, 246]], "regs_out": {"eax": 9607, "ebx": 52891, "ecx": 7353, "edx": 7406, "esi": 28298, "edi": 30578, "ebp": 4694}, "mem_writes": [[655340, 135], [655341, 37], [655338, 0], [655339, 32]], "flags": {"cf": false, "pf": true, "af": false, "zf": true, "sf": false, "of": false}}, {"regs_in": {"ax": 1682, "bx": 12118, "cx": 2292, "dx": 20827, "si": 26873, "di": 16416, "bp": 51233, "sp": 65518}, "segs": {"ds": 8192, "es": 8704, "fs": 9216, "gs": 9728, "ss": 36864}, "mem_in": [[158487, 247]], "regs_out": {"eax": 1682, "ebx": 12118, "ecx": 2292, "edx": 20827, "esi": 26873, "edi": 16416, "ebp": 51233}, "mem_writes": [[655340, 146], [655341, 6], [655338, 0], [655339, 32]], "flags": {"cf": false, "pf": false, "af": false, "zf": false, "sf": false, "of": false}}, {"regs_in": {"ax": 14479, "bx": 24778, "cx": 50500, "dx": 54109, "si": 52979, "di": 25390, "bp": 11963, "sp": 65518}, "segs": {"ds": 8192, "es": 8704, "fs": 9216, "gs": 9728, "ss": 36864}, "mem_in": [[158487, 203]], "regs_out": {"eax": 14479, "ebx": 24778, "ecx": 50500, "edx": 54109, "esi": 52979, "edi": 25390, "ebp": 11963}, "mem_writes": [[655340, 143], [655341, 56], [655338, 0], [655339, 32]], "flags": {"cf": false, "pf": false, "af": false, "zf": false, "sf": false, "of": false}}, {"regs_in": {"ax": 3938, "bx": 13090, "cx": 13989, "dx": 41905, "si": 52728, "di": 37419, "bp": 22286, "sp": 65518}, "segs": {"ds": 8192, "es": 8704, "fs": 9216, "gs": 9728, "ss": 36864}, "mem_in": [[158487, 29]], "regs_out": {"eax": 3938, "ebx": 13090, "ecx": 13989, "edx": 41905, "esi": 52728, "edi": 37419, "ebp": 22286}, "mem_writes": [[655340, 98], [655341, 15], [655338, 0], [655339, 32]], "flags": {"cf": false, "pf": false, "af": false, "zf": false, "sf": false, "of": false}}, {"regs_in": {"ax": 54575, "bx": 33667, "cx": 24556, "dx": 41097, "si": 12344, "di": 42820, "bp": 41238, "sp": 65518}, "segs": {"ds": 8192, "es": 8704, "fs": 9216, "gs": 9728, "ss": 36864}, "mem_in": [[158487, 140]], "regs_out": {"eax": 54575, "ebx": 33667, "ecx": 24556, "edx": 41097, "esi": 12344, "edi": 42820, "ebp": 41238}, "mem_writes": [[655340, 47], [655341, 213], [655338, 0], [655339, 32]], "flags": {"cf": false, "pf": true, "af": false, "zf": true, "sf": false, "of": false}}, {"regs_in": {"ax": 21422, "bx": 52988, "cx": 13161, "dx": 57788, "si": 53639, "di": 48204, "bp": 24846, "sp": 65518}, "segs": {"ds": 8192, "es": 8704, "fs": 9216, "gs": 9728, "ss": 36864}, "mem_in": [[158487, 174]], "regs_out": {"eax": 21422, "ebx": 52988, "ecx": 13161, "edx": 57788, "esi": 53639, "edi": 48204, "ebp": 24846}, "mem_writes": [[655340, 174], [655341, 83], [655338, 0], [655339, 32]], "flags": {"cf": false, "pf": true, "af": false, "zf": true, "sf": false, "of": false}}, {"regs_in": {"ax": 29910, "bx": 63323, "cx": 7167, "dx": 22876, "si": 14207, "di": 25835, "bp": 21915, "sp": 65518}, "segs": {"ds": 8192, "es": 8704, "fs": 9216, "gs": 9728, "ss": 36864}, "mem_in": [[158487, 25]], "regs_out": {"eax": 29910, "ebx": 63323, "ecx": 7167, "edx": 22876, "esi": 14207, "edi": 25835, "ebp": 21915}, "mem_writes": [[655340, 214], [655341, 116], [655338, 0], [655339, 32]], "flags": {"cf": false, "pf": false, "af": false, "zf": false, "sf": false, "of": false}}, {"regs_in": {"ax": 15546, "bx": 59956, "cx": 58770, "dx": 51105, "si": 15723, "di": 33411, "bp": 27865, "sp": 65518}, "segs": {"ds": 8192, "es": 8704, "fs": 9216, "gs": 9728, "ss": 36864}, "mem_in": [[158487, 47]], "regs_out": {"eax": 15546, "ebx": 59956, "ecx": 58770, "edx": 51105, "esi": 15723, "edi": 33411, "ebp": 27865}, "mem_writes": [[655340, 186], [655341, 60], [655338, 0], [655339, 32]], "flags": {"cf": false, "pf": false, "af": false, "zf": false, "sf": false, "of": false}}, {"regs_in": {"ax": 55738, "bx": 690, "cx": 7124, "dx": 23729, "si": 36433, "di": 10168, "bp": 40324, "sp": 65518}, "segs": {"ds": 8192, "es": 8704, "fs": 9216, "gs": 9728, "ss": 36864}, "mem_in": [[158487, 169]], "regs_out": {"eax": 55738, "ebx": 690, "ecx": 7124, "edx": 23729, "esi": 36433, "edi": 10168, "ebp": 40324}, "mem_writes": [[655340, 186], [655341, 217], [655338, 0], [655339, 32]], "flags": {"cf": false, "pf": false, "af": false, "zf": false, "sf": false, "of": false}}, {"regs_in": {"ax": 57387, "bx": 2665, "cx": 62999, "dx": 9157, "si": 34479, "di": 50378, "bp": 52571, "sp": 65518}, "segs": {"ds": 8192, "es": 8704, "fs": 9216, "gs": 9728, "ss": 36864}, "mem_in": [[158487, 220]], "regs_out": {"eax": 57387, "ebx": 2665, "ecx": 62999, "edx": 9157, "esi": 34479, "edi": 50378, "ebp": 52571}, "mem_writes": [[655340, 43], [655341, 224], [655338, 0], [655339, 32]], "flags": {"cf": false, "pf": true, "af": false, "zf": true, "sf": false, "of": false}}, {"regs_in": {"ax": 7095, "bx": 50918, "cx": 40131, "dx": 62373, "si": 50551, "di": 8031, "bp": 61023, "sp": 65518}, "segs": {"ds": 8192, "es": 8704, "fs": 9216, "gs": 9728, "ss": 36864}, "mem_in": [[158487, 11]], "regs_out": {"eax": 7095, "ebx": 50918, "ecx": 40131, "edx": 62373, "esi": 50551, "edi": 8031, "ebp": 61023}, "mem_writes": [[655340, 183], [655341, 27], [655338, 0], [655339, 32]], "flags": {"cf": false, "pf": false, "af": false, "zf": false, "sf": false, "of": false}}, {"regs_in": {"ax": 50895, "bx": 3847, "cx": 41523, "dx": 55497, "si": 39397, "di": 39127, "bp": 11948, "sp": 65518}, "segs": {"ds": 8192, "es": 8704, "fs": 9216, "gs": 9728, "ss": 36864}, "mem_in": [[158487, 160]], "regs_out": {"eax": 50895, "ebx": 3847, "ecx": 41523, "edx": 55497, "esi": 39397, "edi": 39127, "ebp": 11948}, "mem_writes": [[655340, 207], [655341, 198], [655338, 0], [655339, 32]], "flags": {"cf": false, "pf": true, "af": false, "zf": true, "sf": false, "of": false}}, {"regs_in": {"ax": 21302, "bx": 42771, "cx": 9250, "dx": 6654, "si": 47366, "di": 62491, "bp": 39494, "sp": 65518}, "segs": {"ds": 8192, "es": 8704, "fs": 9216, "gs": 9728, "ss": 36864}, "mem_in": [[158487, 142]], "regs_out": {"eax": 21302, "ebx": 42771, "ecx": 9250, "edx": 6654, "esi": 47366, "edi": 62491, "ebp": 39494}, "mem_writes": [[655340, 54], [655341, 83], [655338, 0], [655339, 32]], "flags": {"cf": false, "pf": true, "af": false, "zf": true, "sf": false, "of": false}}, {"regs_in": {"ax": 64334, "bx": 28480, "cx": 48398, "dx": 2096, "si": 31724, "di": 15923, "bp": 24098, "sp": 65518}, "segs": {"ds": 8192, "es": 8704, "fs": 9216, "gs": 9728, "ss": 36864}, "mem_in": [[158487, 105]], "regs_out": {"eax": 64334, "ebx": 28480, "ecx": 48398, "edx": 2096, "esi": 31724, "edi": 15923, "ebp": 24098}, "mem_writes": [[655340, 78], [655341, 251], [655338, 0], [655339, 32]], "flags": {"cf": false, "pf": false, "af": false, "zf": false, "sf": false, "of": false}}, {"regs_in": {"ax": 22703, "bx": 39547, "cx": 48941, "dx": 10473, "si": 5241, "di": 21936, "bp": 63643, "sp": 65518}, "segs": {"ds": 8192, "es": 8704, "fs": 9216, "gs": 9728, "ss": 36864}, "mem_in": [[158487, 18]], "regs_out": {"eax": 22703, "ebx": 39547, "ecx": 48941, "edx": 10473, "esi": 5241, "edi": 21936, "ebp": 63643}, "mem_writes": [[655340, 175], [655341, 88], [655338, 0], [655339, 32]], "flags": {"cf": false, "pf": true, "af": false, "zf": true, "sf": false, "of": false}}, {"regs_in": {"ax": 10052, "bx": 26169, "cx": 28115, "dx": 17474, "si": 8099, "di": 13974, "bp": 43615, "sp": 65518}, "segs": {"ds": 8192, "es": 8704, "fs": 9216, "gs": 9728, "ss": 36864}, "mem_in": [[158487, 53]], "regs_out": {"eax": 10052, "ebx": 26169, "ecx": 28115, "edx": 17474, "esi": 8099, "edi": 13974, "ebp": 43615}, "mem_writes": [[655340, 68], [655341, 39], [655338, 0], [655339, 32]], "flags": {"cf": false, "pf": false, "af": false, "zf": false, "sf": false, "of": false}}, {"regs_in": {"ax": 35472, "bx": 18915, "cx": 14806, "dx": 60298, "si": 41545, "di": 37561, "bp": 64244, "sp": 65518}, "segs": {"ds": 8192, "es": 8704, "fs": 9216, "gs": 9728, "ss": 36864}, "mem_in": [[158487, 100]], "regs_out": {"eax": 35472, "ebx": 18915, "ecx": 14806, "edx": 60298, "esi": 41545, "edi": 37561, "ebp": 64244}, "mem_writes": [[655340, 144], [655341, 138], [655338, 0], [655339, 32]], "flags": {"cf": false, "pf": true, "af": false, "zf": true, "sf": false, "of": false}}, {"regs_in": {"ax": 19459, "bx": 20057, "cx": 38219, "dx": 61425, "si": 58433, "di": 43760, "bp": 33025, "sp": 65518}, "segs": {"ds": 8192, "es": 8704, "fs": 9216, "gs": 9728, "ss": 36864}, "mem_in": [[158487, 140]], "regs_out": {"eax": 19459, "ebx": 20057, "ecx": 38219, "edx": 61425, "esi": 58433, "edi": 43760, "ebp": 33025}, "mem_writes": [[655340, 3], [655341, 76], [655338, 0], [655339, 32]], "flags": {"cf": false, "pf": true, "af": false, "zf": true, "sf": false, "of": false}}, {"regs_in": {"ax": 16820, "bx": 33409, "cx": 48131, "dx": 7802, "si": 49237, "di": 32955, "bp": 35420, "sp": 65518}, "segs": {"ds": 8192, "es": 8704, "fs": 9216, "gs": 9728, "ss": 36864}, "mem_in": [[158487, 158]], "regs_out": {"eax": 16820, "ebx": 33409, "ecx": 48131, "edx": 7802, "esi": 49237, "edi": 32955, "ebp": 35420}, "mem_writes": [[655340, 180], [655341, 65], [655338, 0], [655339, 32]], "flags": {"cf": false, "pf": true, "af": false, "zf": true, "sf": false, "of": false}}, {"regs_in": {"ax": 55, "bx": 13288, "cx": 55763, "dx": 8182, "si": 23598, "di": 8598, "bp": 8943, "sp": 65518}, "segs": {"ds": 8192, "es": 8704, "fs": 9216, "gs": 9728, "ss": 36864}, "mem_in": [[158487, 6]], "regs_out": {"eax": 55, "ebx": 13288, "ecx": 55763, "edx": 8182, "esi": 23598, "edi": 8598, "ebp": 8943}, "mem_writes": [[655340, 55], [655341, 0], [655338, 0], [655339, 32]], "flags": {"cf": false, "pf": true, "af": false, "zf": true, "sf": false, "of": false}}, {"regs_in": {"ax": 7188, "bx": 40214, "cx": 59126, "dx": 60041, "si": 58159, "di": 18207, "bp": 25755, "sp": 65518}, "segs": {"ds": 8192, "es": 8704, "fs": 9216, "gs": 9728, "ss": 36864}, "mem_in": [[158487, 173]], "regs_out": {"eax": 7188, "ebx": 40214, "ecx": 59126, "edx": 60041, "esi": 58159, "edi": 18207, "ebp": 25755}, "mem_writes": [[655340, 20], [655341, 28], [655338, 0], [655339, 32]], "flags": {"cf": false, "pf": false, "af": false, "zf": false, "sf": false, "of": false}}, {"regs_in": {"ax": 47779, "bx": 21548, "cx": 19277, "dx": 1817, "si": 14222, "di": 63063, "bp": 43359, "sp": 65518}, "segs": {"ds": 8192, "es": 8704, "fs": 9216, "gs": 9728, "ss": 36864}, "mem_in": [[158487, 239]], "regs_out": {"eax": 47779, "ebx": 21548, "ecx": 19277, "edx": 1817, "esi": 14222, "edi": 63063, "ebp": 43359}, "mem_writes": [[655340, 163], [655341, 186], [655338, 0], [655339, 32]], "flags": {"cf": false, "pf": false, "af": false, "zf": false, "sf": false, "of": false}}, {"regs_in": {"ax": 821, "bx": 58235, "cx": 43364, "dx": 51228, "si": 20609, "di": 59680, "bp": 37209, "sp": 65518}, "segs": {"ds": 8192, "es": 8704, "fs": 9216, "gs": 9728, "ss": 36864}, "mem_in": [[158487, 23]], "regs_out": {"eax": 821, "ebx": 58235, "ecx": 43364, "edx": 51228, "esi": 20609, "edi": 59680, "ebp": 37209}, "mem_writes": [[655340, 53], [655341, 3], [655338, 0], [655339, 32]], "flags": {"cf": false, "pf": false, "af": false, "zf": false, "sf": false, "of": false}}, {"regs_in": {"ax": 50089, "bx": 20430, "cx": 3827, "dx": 62327, "si": 48831, "di": 56357, "bp": 61293, "sp": 65518}, "segs": {"ds": 8192, "es": 8704, "fs": 9216, "gs": 9728, "ss": 36864}, "mem_in": [[158487, 114]], "regs_out": {"eax": 50089, "ebx": 20430, "ecx": 3827, "edx": 62327, "esi": 48831, "edi": 56357, "ebp": 61293}, "mem_writes": [[655340, 169], [655341, 195], [655338, 0], [655339, 32]], "flags": {"cf": false, "pf": true, "af": false, "zf": true, "sf": false, "of": false}}, {"regs_in": {"ax": 28114, "bx": 63242, "cx": 33381, "dx": 29906, "si": 19158, "di": 24514, "bp": 33377, "sp": 65518}, "segs": {"ds": 8192, "es": 8704, "fs": 9216, "gs": 9728, "ss": 36864}, "mem_in": [[158487, 27]], "regs_out": {"eax": 28114, "ebx": 63242, "ecx": 33381, "edx": 29906, "esi": 19158, "edi": 24514, "ebp": 33377}, "mem_writes": [[655340, 210], [655341, 109], [655338, 0], [655339, 32]], "flags": {"cf": false, "pf": false, "af": false, "zf": false, "sf": false, "of": false}}, {"regs_in": {"ax": 58321, "bx": 45989, "cx": 39238, "dx": 8126, "si": 51695, "di": 44268, "bp": 17517, "sp": 65518}, "segs": {"ds": 8192, "es": 8704, "fs": 9216, "gs": 9728, "ss": 36864}, "mem_in": [[158487, 23]], "regs_out": {"eax": 58321, "ebx": 45989, "ecx": 39238, "edx": 8126, "esi": 51695, "edi": 44268, "ebp": 17517}, "mem_writes": [[655340, 209], [655341, 227], [655338, 0], [655339, 32]], "flags": {"cf": false, "pf": false, "af": false, "zf": false, "sf": false, "of": false}}, {"regs_in": {"ax": 45144, "bx": 978, "cx": 838, "dx": 64716, "si": 8241, "di": 24835, "bp": 4185, "sp": 65518}, "segs": {"ds": 8192, "es": 8704, "fs": 9216, "gs": 9728, "ss": 36864}, "mem_in": [[158487, 170]], "regs_out": {"eax": 45144, "ebx": 978, "ecx": 838, "edx": 64716, "esi": 8241, "edi": 24835, "ebp": 4185}, "mem_writes": [[655340, 88], [655341, 176], [655338, 0], [655339, 32]], "flags": {"cf": false, "pf": true, "af": false, "zf": true, "sf": false, "of": false}}, {"regs_in": {"ax": 51475, "bx": 26774, "cx": 35531, "dx": 45656, "si": 44381, "di": 38831, "bp": 8039, "sp": 65518}, "segs": {"ds": 8192, "es": 8704, "fs": 9216, "gs": 9728, "ss": 36864}, "mem_in": [[158487, 208]], "regs_out": {"eax": 51475, "ebx": 26774, "ecx": 35531, "edx": 45656, "esi": 44381, "edi": 38831, "ebp": 8039}, "mem_writes": [[655340, 19], [655341, 201], [655338, 0], [655339, 32]], "flags": {"cf": false, "pf": true, "af": false, "zf": true, "sf": false, "of": false}}, {"regs_in": {"ax": 10221, "bx": 61803, "cx": 1340, "dx": 55359, "si": 5554, "di": 61839, "bp": 7867, "sp": 65518}, "segs": {"ds": 8192, "es": 8704, "fs": 9216, "gs": 9728, "ss": 36864}, "mem_in": [[158487, 81]], "regs_out": {"eax": 10221, "ebx": 61803, "ecx": 1340, "edx": 55359, "esi": 5554, "edi": 61839, "ebp": 7867}, "mem_writes": [[655340, 237], [655341, 39], [655338, 0], [655339, 32]], "flags": {"cf": false, "pf": false, "af": false, "zf": false, "sf": false, "of": false}}, {"regs_in": {"ax": 51175, "bx": 64998, "cx": 18776, "dx": 40364, "si": 62713, "di": 43517, "bp": 12902, "sp": 65518}, "segs": {"ds": 8192, "es": 8704, "fs": 9216, "gs": 9728, "ss": 36864}, "mem_in": [[158487, 16]], "regs_out": {"eax": 51175, "ebx": 64998, "ecx": 18776, "edx": 40364, "esi": 62713, "edi": 43517, "ebp": 12902}, "mem_writes": [[655340, 231], [655341, 199], [655338, 0], [655339, 32]], "flags": {"cf": false, "pf": true, "af": false, "zf": true, "sf": false, "of": false}}, {"regs_in": {"ax": 29402, "bx": 618, "cx": 4803, "dx": 54291, "si": 44993, "di": 59602, "bp": 33979, "sp": 65518}, "segs": {"ds": 8192, "es": 8704, "fs": 9216, "gs": 9728, "ss": 36864}, "mem_in": [[158487, 217]], "regs_out": {"eax": 29402, "ebx": 618, "ecx": 4803, "edx": 54291, "esi": 44993, "edi": 59602, "ebp": 33979}, "mem_writes": [[655340, 218], [655341, 114], [655338, 0], [655339, 32]], "flags": {"cf": false, "pf": false, "af": false, "zf": false, "sf": false, "of": false}}, {"regs_in": {"ax": 8069, "bx": 2163, "cx": 28518, "dx": 46183, "si": 54131, "di": 35398, "bp": 39954, "sp": 65518}, "segs": {"ds": 8192, "es": 8704, "fs": 9216, "gs": 9728, "ss": 36864}, "mem_in": [[158487, 227]], "regs_out": {"eax": 8069, "ebx": 2163, "ecx": 28518, "edx": 46183, "esi": 54131, "edi": 35398, "ebp": 39954}, "mem_writes": [[655340, 133], [655341, 31], [655338, 0], [655339, 32]], "flags": {"cf": false, "pf": false, "af": false, "zf": false, "sf": false, "of": false}}, {"regs_in": {"ax": 59967, "bx": 45710, "cx": 6306, "dx": 4462, "si": 30881, "di": 14637, "bp": 50593, "sp": 65518}, "segs": {"ds": 8192, "es": 8704, "fs": 9216, "gs": 9728, "ss": 36864}, "mem_in": [[158487, 80]], "regs_out": {"eax": 59967, "ebx": 45710, "ecx": 6306, "edx": 4462, "esi": 30881, "edi": 14637, "ebp": 50593}, "mem_writes": [[655340, 63], [655341, 234], [655338, 0], [655339, 32]], "flags": {"cf": false, "pf": true, "af": false, "zf": true, "sf": false, "of": false}}, {"regs_in": {"ax": 47268, "bx": 1849, "cx": 25814, "dx": 6314, "si": 17055, "di": 11459, "bp": 10295, "sp": 65518}, "segs": {"ds": 8192, "es": 8704, "fs": 9216, "gs": 9728, "ss": 36864}, "mem_in": [[158487, 229]], "regs_out": {"eax": 47268, "ebx": 1849, "ecx": 25814, "edx": 6314, "esi": 17055, "edi": 11459, "ebp": 10295}, "mem_writes": [[655340, 164], [655341, 184], [655338, 0], [655339, 32]], "flags": {"cf": false, "pf": false, "af": false, "zf": false, "sf": false, "of": false}}, {"regs_in": {"ax": 44176, "bx": 9220, "cx": 1262, "dx": 29699, "si": 37680, "di": 52149, "bp": 5144, "sp": 65518}, "segs": {"ds": 8192, "es": 8704, "fs": 9216, "gs": 9728, "ss": 36864}, "mem_in": [[158487, 195]], "regs_out": {"eax": 44176, "ebx": 9220, "ecx": 1262, "edx": 29699, "esi": 37680, "edi": 52149, "ebp": 5144}, "mem_writes": [[655340, 144], [655341, 172], [655338, 0], [655339, 32]], "flags": {"cf": false, "pf": false, "af": false, "zf": false, "sf": false, "of": false}}, {"regs_in": {"ax": 42054, "bx": 53438, "cx": 46171, "dx": 24060, "si": 63997, "di": 27478, "bp": 31407, "sp": 65518}, "segs": {"ds": 8192, "es": 8704, "fs": 9216, "gs": 9728, "ss": 36864}, "mem_in": [[158487, 159]], "regs_out": {"eax": 42054, "ebx": 53438, "ecx": 46171, "edx": 24060, "esi": 63997, "edi": 27478, "ebp": 31407}, "mem_writes": [[655340, 70], [655341, 164], [655338, 0], [655339, 32]], "flags": {"cf": false, "pf": false, "af": false, "zf": false, "sf": false, "of": false}}, {"regs_in": {"ax": 14948, "bx": 19767, "cx": 19147, "dx": 23975, "si": 53365, "di": 15084, "bp": 40689, "sp": 65518}, "segs": {"ds": 8192, "es": 8704, "fs": 9216, "gs": 9728, "ss": 36864}, "mem_in": [[158487, 40]], "regs_out": {"eax": 14948, "ebx": 19767, "ecx": 19147, "edx": 23975, "esi": 53365, "edi": 15084, "ebp": 40689}, "mem_writes": [[655340, 100], [655341, 58], [655338, 0], [655339, 32]], "flags": {"cf": false, "pf": true, "af": false, "zf": true, "sf": false, "of": false}}, {"regs_in": {"ax": 50777, "bx": 16212, "cx": 55337, "dx": 34372, "si": 43855, "di": 4072, "bp": 62008, "sp": 65518}, "segs": {"ds": 8192, "es": 8704, "fs": 9216, "gs": 9728, "ss": 36864}, "mem_in": [[158487, 229]], "regs_out": {"eax": 50777, "ebx": 16212, "ecx": 55337, "edx": 34372, "esi": 43855, "edi": 4072, "ebp": 62008}, "mem_writes": [[655340, 89], [655341, 198], [655338, 0], [655339, 32]], "flags": {"cf": false, "pf": false, "af": false, "zf": false, "sf": false, "of": false}}, {"regs_in": {"ax": 57285, "bx": 41595, "cx": 65314, "dx": 59783, "si": 2413, "di": 56855, "bp": 5216, "sp": 65518}, "segs": {"ds": 8192, "es": 8704, "fs": 9216, "gs": 9728, "ss": 36864}, "mem_in": [[158487, 104]], "regs_out": {"eax": 57285, "ebx": 41595, "ecx": 65314, "edx": 59783, "esi": 2413, "edi": 56855, "ebp": 5216}, "mem_writes": [[655340, 197], [655341, 223], [655338, 0], [655339, 32]], "flags": {"cf": false, "pf": true, "af": false, "zf": true, "sf": false, "of": false}}, {"regs_in": {"ax": 24485, "bx": 9261, "cx": 45390, "dx": 19263, "si": 58623, "di": 61364, "bp": 31369, "sp": 65518}, "segs": {"ds": 8192, "es": 8704, "fs": 9216, "gs": 9728, "ss": 36864}, "mem_in": [[158487, 32]], "regs_out": {"eax": 24485, "ebx": 9261, "ecx": 45390, "edx": 19263, "esi": 58623, "edi": 61364, "ebp": 31369}, "mem_writes": [[655340, 165], [655341, 95], [655338, 0], [655339, 32]], "flags": {"cf": false, "pf": true, "af": false, "zf": true, "sf": false, "of": false}}, {"regs_in": {"ax": 48466, "bx": 12231, "cx": 39201, "dx": 13789, "si": 49899, "di": 2675, "bp": 25015, "sp": 65518}, "segs": {"ds": 8192, "es": 8704, "fs": 9216, "gs": 9728, "ss": 36864}, "mem_in": [[158487, 199]], "regs_out": {"eax": 48466, "ebx": 12231, "ecx": 39201, "edx": 13789, "esi": 49899, "edi": 2675, "ebp": 25015}, "mem_writes": [[655340, 82], [655341, 189], [655338, 0], [655339, 32]], "flags": {"cf": false, "pf": false, "af": false, "zf": false, "sf": false, "of": false}}, {"regs_in": {"ax": 20879, "bx": 35651, "cx": 6407, "dx": 40768, "si": 27529, "di": 14772, "bp": 18295, "sp": 65518}, "segs": {"ds": 8192, "es": 8704, "fs": 9216, "gs": 9728, "ss": 36864}, "mem_in": [[158487, 218]], "regs_out": {"eax": 20879, "ebx": 35651, "ecx": 6407, "edx": 40768, "esi": 27529, "edi": 14772, "ebp": 18295}, "mem_writes": [[655340, 143], [655341, 81], [655338, 0], [655339, 32]], "flags": {"cf": false, "pf": true, "af": false, "zf": true, "sf": false, "of": false}}, {"regs_in": {"ax": 21919, "bx": 28691, "cx": 44104, "dx": 38832, "si": 31356, "di": 51551, "bp": 11215, "sp": 65518}, "segs": {"ds": 8192, "es": 8704, "fs": 9216, "gs": 9728, "ss": 36864}, "mem_in": [[158487, 221]], "regs_out": {"eax": 21919, "ebx": 28691, "ecx": 44104, "edx": 38832, "esi": 31356, "edi": 51551, "ebp": 11215}, "mem_writes": [[655340, 159], [655341, 85], [655338, 0], [655339, 32]], "flags": {"cf": false, "pf": false, "af": false, "zf": false, "sf": false, "of": false}}, {"regs_in": {"ax": 61608, "bx": 28040, "cx": 43622, "dx": 23835, "si": 27999, "di": 29426, "bp": 13409, "sp": 65518}, "segs": {"ds": 8192, "es": 8704, "fs": 9216, "gs": 9728, "ss": 36864}, "mem_in": [[158487, 248]], "regs_out": {"eax": 61608, "ebx": 28040, "ecx": 43622, "edx": 23835, "esi": 27999, "edi": 29426, "ebp": 13409}, "mem_writes": [[655340, 168], [655341, 240], [655338, 0], [655339, 32]], "flags": {"cf": false, "pf": true, "af": false, "zf": true, "sf": false, "of": false}}, {"regs_in": {"ax": 20029, "bx": 39291, "cx": 29789, "dx": 21575, "si": 10597, "di": 17484, "bp": 34757, "sp": 65518}, "segs": {"ds": 8192, "es": 8704, "fs": 9216, "gs": 9728, "ss": 36864}, "mem_in": [[158487, 222]], "regs_out": {"eax": 20029, "ebx": 39291, "ecx": 29789, "edx": 21575, "esi": 10597, "edi": 17484, "ebp": 34757}, "mem_writes": [[655340, 61], [655341, 78], [655338, 0], [655339, 32]], "flags": {"cf": false, "pf": true, "af": false, "zf": true, "sf": false, "of": false}}, {"regs_in": {"ax": 21052, "bx": 37434, "cx": 26439, "dx": 41534, "si": 10056, "di": 46432, "bp": 54247, "sp": 65518}, "segs": {"ds": 8192, "es": 8704, "fs": 9216, "gs": 9728, "ss": 36864}, "mem_in": [[158487, 182]], "regs_out": {"eax": 21052, "ebx": 37434, "ecx": 26439, "edx": 41534, "esi": 10056, "edi": 46432, "ebp": 54247}, "mem_writes": [[655340, 60], [655341, 82], [655338, 0], [655339, 32]], "flags": {"cf": false, "pf": true, "af": false, "zf": true, "sf": false, "of": false}}, {"regs_in": {"ax": 8185, "bx": 52275, "cx": 41663, "dx": 60846, "si": 9412, "di": 8514, "bp": 61039, "sp": 65518}, "segs": {"ds": 8192, "es": 8704, "fs": 9216, "gs": 9728, "ss": 36864}, "mem_in": [[158487, 97]], "regs_out": {"eax": 8185, "ebx": 52275, "ecx": 41663, "edx": 60846, "esi": 9412, "edi": 8514, "ebp": 61039}, "mem_writes": [[655340, 249], [655341, 31], [655338, 0], [655339, 32]], "flags": {"cf": false, "pf": false, "af": false, "zf": false, "sf": false, "of": false}}, {"regs_in": {"ax": 7157, "bx": 17602, "cx": 41618, "dx": 55, "si": 10858, "di": 20212, "bp": 31194, "sp": 65518}, "segs": {"ds": 8192, "es": 8704, "fs": 9216, "gs": 9728, "ss": 36864}, "mem_in": [[158487, 47]], "regs_out": {"eax": 7157, "ebx": 17602, "ecx": 41618, "edx": 55, "esi": 10858, "edi": 20212, "ebp": 31194}, "mem_writes": [[655340, 245], [655341, 27], [655338, 0], [655339, 32]], "flags": {"cf": false, "pf": false, "af": false, "zf": false, "sf": false, "of": false}}, {"regs_in": {"ax": 23186, "bx": 64426, "cx": 52609, "dx": 38971, "si": 27247, "di": 63383, "bp": 8912, "sp": 65518}, "segs": {"ds": 8192, "es": 8704, "fs": 9216, "gs": 9728, "ss": 36864}, "mem_in": [[158487, 9]], "regs_out": {"eax": 23186, "ebx": 64426, "ecx": 52609, "edx": 38971, "esi": 27247, "edi": 63383, "ebp": 8912}, "mem_writes": [[655340, 146], [655341, 90], [655338, 0], [655339, 32]], "flags": {"cf": false, "pf": false, "af": false, "zf": false, "sf": false, "of": false}}, {"regs_in": {"ax": 42205, "bx": 63065, "cx": 25266, "dx": 39738, "si": 46311, "di": 33393, "bp": 28065, "sp": 65518}, "segs": {"ds": 8192, "es": 8704, "fs": 9216, "gs": 9728, "ss": 36864}, "mem_in": [[158487, 79]], "regs_out": {"eax": 42205, "ebx": 63065, "ecx": 25266, "edx": 39738, "esi": 46311, "edi": 33393, "ebp": 28065}, "mem_writes": [[655340, 221], [655341, 164], [655338, 0], [655339, 32]], "flags": {"cf": false, "pf": false, "af": false, "zf": false, "sf": false, "of": false}}, {"regs_in": {"ax": 31419, "bx": 13674, "cx": 55486, "dx": 3287, "si": 1066, "di": 64286, "bp": 25417, "sp": 65518}, "segs": {"ds": 8192, "es": 8704, "fs": 9216, "gs": 9728, "ss": 36864}, "mem_in": [[158487, 181]], "regs_out": {"eax": 31419, "ebx": 13674, "ecx": 55486, "edx": 3287, "esi": 1066, "edi": 64286, "ebp": 25417}, "mem_writes": [[655340, 187], [655341, 122], [655338, 0], [655339, 32]], "flags": {"cf": false, "pf": false, "af": false, "zf": false, "sf": false, "of": false}}, {"regs_in": {"ax": 56115, "bx": 39700, "cx": 49140, "dx": 14943, "si": 7073, "di": 11933, "bp": 64954, "sp": 65518}, "segs": {"ds": 8192, "es": 8704, "fs": 9216, "gs": 9728, "ss": 36864}, "mem_in": [[158487, 111]], "regs_out": {"eax": 56115, "ebx": 39700, "ecx": 49140, "edx": 14943, "esi": 7073, "edi": 11933, "ebp": 64954}, "mem_writes": [[655340, 51], [655341, 219], [655338, 0], [655339, 32]], "flags": {"cf": false, "pf": false, "af": false, "zf": false, "sf": false, "of": false}}, {"regs_in": {"ax": 45876, "bx": 11556, "cx": 10064, "dx": 62958, "si": 44415, "di": 4642, "bp": 65076, "sp": 65518}, "segs": {"ds": 8192, "es": 8704, "fs": 9216, "gs": 9728, "ss": 36864}, "mem_in": [[158487, 2]], "regs_out": {"eax": 45876, "ebx": 11556, "ecx": 10064, "edx": 62958, "esi": 44415, "edi": 4642, "ebp": 65076}, "mem_writes": [[655340, 52], [655341, 179], [655338, 0], [655339, 32]], "flags": {"cf": false, "pf": true, "af": false, "zf": true, "sf": false, "of": false}}, {"regs_in": {"ax": 22808, "bx": 64610, "cx": 55376, "dx": 63755, "si": 15333, "di": 41224, "bp": 29971, "sp": 65518}, "segs": {"ds": 8192, "es": 8704, "fs": 9216, "gs": 9728, "ss": 36864}, "mem_in": [[158487, 198]], "regs_out": {"eax": 22808, "ebx": 64610, "ecx": 55376, "edx": 63755, "esi": 15333, "edi": 41224, "ebp": 29971}, "mem_writes": [[655340, 24], [655341, 89], [655338, 0], [655339, 32]], "flags": {"cf": false, "pf": true, "af": false, "zf": true, "sf": false, "of": false}}, {"regs_in": {"ax": 33806, "bx": 43548, "cx": 16577, "dx": 59245, "si": 52433, "di": 54369, "bp": 13779, "sp": 65518}, "segs": {"ds": 8192, "es": 8704, "fs": 9216, "gs": 9728, "ss": 36864}, "mem_in": [[158487, 58]], "regs_out": {"eax": 33806, "ebx": 43548, "ecx": 16577, "edx": 59245, "esi": 52433, "edi": 54369, "ebp": 13779}, "mem_writes": [[655340, 14], [655341, 132], [655338, 0], [655339, 32]], "flags": {"cf": false, "pf": true, "af": false, "zf": true, "sf": false, "of": false}}, {"regs_in": {"ax": 3547, "bx": 61138, "cx": 24789, "dx": 41598, "si": 37501, "di": 28050, "bp": 63172, "sp": 65518}, "segs": {"ds": 8192, "es": 8704, "fs": 9216, "gs": 9728, "ss": 36864}, "mem_in": [[158487, 238]], "regs_out": {"eax": 3547, "ebx": 61138, "ecx": 24789, "edx": 41598, "esi": 37501, "edi": 28050, "ebp": 63172}, "mem_writes": [[655340, 219], [655341, 13], [655338, 0], [655339, 32]], "flags": {"cf": false, "pf": true, "af": false, "zf": true, "sf": false, "of": false}}, {"regs_in": {"ax": 24521, "bx": 48724, "cx": 61142, "dx": 25418, "si": 46226, "di": 34725, "bp": 61336, "sp": 65518}, "segs": {"ds": 8192, "es": 8704, "fs": 9216, "gs": 9728, "ss": 36864}, "mem_in": [[158487, 82]], "regs_out": {"eax": 24521, "ebx": 48724, "ecx": 61142, "edx": 25418, "esi": 46226, "edi": 34725, "ebp": 61336}, "mem_writes": [[655340, 201], [655341, 95], [655338, 0], [655339, 32]], "flags": {"cf": false, "pf": true, "af": false, "zf": true, "sf": false, "of": false}}, {"regs_in": {"ax": 10641, "bx": 57061, "cx": 42919, "dx": 34782, "si": 46983, "di": 14304, "bp": 32472, "sp": 65518}, "segs": {"ds": 8192, "es": 8704, "fs": 9216, "gs": 9728, "ss": 36864}, "mem_in": [[158487, 113]], "regs_out": {"eax": 10641, "ebx": 57061, "ecx": 42919, "edx": 34782, "esi": 46983, "edi": 14304, "ebp": 32472}, "mem_writes": [[655340, 145], [655341, 41], [655338, 0], [655339, 32]], "flags": {"cf": false, "pf": false, "af": false, "zf": false, "sf": false, "of": false}}, {"regs_in": {"ax": 15642, "bx": 3453, "cx": 29630, "dx": 52121, "si": 35270, "di": 5958, "bp": 51524, "sp": 65518}, "segs": {"ds": 8192, "es": 8704, "fs": 9216, "gs": 9728, "ss": 36864}, "mem_in": [[158487, 174]], "regs_out": {"eax": 15642, "ebx": 3453, "ecx": 29630, "edx": 52121, "esi": 35270, "edi": 5958, "ebp": 51524}, "mem_writes": [[655340, 26], [655341, 61], [655338, 0], [655339, 32]], "flags": {"cf": false, "pf": true, "af": false, "zf": true, "sf": false, "of": false}}, {"regs_in": {"ax": 47615, "bx": 46191, "cx": 11904, "dx": 60822, "si": 41514, "di": 9541, "bp": 63697, "sp": 65518}, "segs": {"ds": 8192, "es": 8704, "fs": 9216, "gs": 9728, "ss": 36864}, "mem_in": [[158487, 51]], "regs_out": {"eax": 47615, "ebx": 46191, "ecx": 11904, "edx": 60822, "esi": 41514, "edi": 9541, "ebp": 63697}, "mem_writes": [[655340, 255], [655341, 185], [655338, 0], [655339, 32]], "flags": {"cf": false, "pf": false, "af": false, "zf": false, "sf": false, "of": false}}, {"regs_in": {"ax": 15550, "bx": 52287, "cx": 27265, "dx": 36652, "si": 240, "di": 45316, "bp": 41662, "sp": 65518}, "segs": {"ds": 8192, "es": 8704, "fs": 9216, "gs": 9728, "ss": 36864}, "mem_in": [[158487, 15]], "regs_out": {"eax": 15550, "ebx": 52287, "ecx": 27265, "edx": 36652, "esi": 240, "edi": 45316, "ebp": 41662}, "mem_writes": [[655340, 190], [655341, 60], [655338, 0], [655339, 32]], "flags": {"cf": false, "pf": false, "af": false, "zf": false, "sf": false, "of": false}}, {"regs_in": {"ax": 4306, "bx": 7670, "cx": 29738, "dx": 64292, "si": 45562, "di": 47989, "bp": 52889, "sp": 65518}, "segs": {"ds": 8192, "es": 8704, "fs": 9216, "gs": 9728, "ss": 36864}, "mem_in": [[158487, 194]], "regs_out": {"eax": 4306, "ebx": 7670, "ecx": 29738, "edx": 64292, "esi": 45562, "edi": 47989, "ebp": 52889}, "mem_writes": [[655340, 210], [655341, 16], [655338, 0], [655339, 32]], "flags": {"cf": false, "pf": true, "af": false, "zf": true, "sf": false, "of": false}}, {"regs_in": {"ax": 51110, "bx": 55871, "cx": 49695, "dx": 49835, "si": 36436, "di": 1098, "bp": 38670, "sp": 65518}, "segs": {"ds": 8192, "es": 8704, "fs": 9216, "gs": 9728, "ss": 36864}, "mem_in": [[158487, 216]], "regs_out": {"eax": 51110, "ebx": 55871, "ecx": 49695, "edx": 49835, "esi": 36436, "edi": 1098, "ebp": 38670}, "mem_writes": [[655340, 166], [655341, 199], [655338, 0], [655339, 32]], "flags": {"cf": false, "pf": true, "af": false, "zf": true, "sf": false, "of": false}}, {"regs_in": {"ax": 17078, "bx": 56357, "cx": 45107, "dx": 40521, "si": 37525, "di": 49330, "bp": 62734, "sp": 65518}, "segs": {"ds": 8192, "es": 8704, "fs": 9216, "gs": 9728, "ss": 36864}, "mem_in": [[158487, 47]], "regs_out": {"eax": 17078, "ebx": 56357, "ecx": 45107, "edx": 40521, "esi": 37525, "edi": 49330, "ebp": 62734}, "mem_writes": [[655340, 182], [655341, 66], [655338, 0], [655339, 32]], "flags": {"cf": false, "pf": false, "af": false, "zf": false, "sf": false, "of": false}}, {"regs_in": {"ax": 39301, "bx": 19588, "cx": 6879, "dx": 26598, "si": 22317, "di": 4725, "bp": 55545, "sp": 65518}, "segs": {"ds": 8192, "es": 8704, "fs": 9216, "gs": 9728, "ss": 36864}, "mem_in": [[158487, 216]], "regs_out": {"eax": 39301, "ebx": 19588, "ecx": 6879, "edx": 26598, "esi": 22317, "edi": 4725, "ebp": 55545}, "mem_writes": [[655340, 133], [655341, 153], [655338, 0], [655339, 32]], "flags": {"cf": false, "pf": true, "af": false, "zf": true, "sf": false, "of": false}}, {"regs_in": {"ax": 53668, "bx": 23195, "cx": 26172, "dx": 52410, "si": 34768, "di": 56395, "bp": 20102, "sp": 65518}, "segs": {"ds": 8192, "es": 8704, "fs": 9216, "gs": 9728, "ss": 36864}, "mem_in": [[158487, 150]], "regs_out": {"eax": 53668, "ebx": 23195, "ecx": 26172, "edx": 52410, "esi": 34768, "edi": 56395, "ebp": 20102}, "mem_writes": [[655340, 164], [655341, 209], [655338, 0], [655339, 32]], "flags": {"cf": false, "pf": true, "af": false, "zf": true, "sf": false, "of": false}}, {"regs_in": {"ax": 44200, "bx": 14192, "cx": 33234, "dx": 32609, "si": 62511, "di": 22866, "bp": 43773, "sp": 65518}, "segs": {"ds": 8192, "es": 8704, "fs": 9216, "gs": 9728, "ss": 36864}, "mem_in": [[158487, 206]], "regs_out": {"eax": 44200, "ebx": 14192, "ecx": 33234, "edx": 32609, "esi": 62511, "edi": 22866, "ebp": 43773}, "mem_writes": [[655340, 168], [655341, 172], [655338, 0], [655339, 32]], "flags": {"cf": false, "pf": true, "af": false, "zf": true, "sf": false, "of": false}}]